Workbook
Name All_in_Development_Cost: Overview!$D$27
Name Amortization_period: Overview!$D$47
Name Annual_Degradation: Overview!$D$19
Name Asset_Mgmt: Overview!$D$34
Name Capacity_Factor: Overview!$D$18
Name CO2_offset: Overview!$D$50
Name Construction_Start_Date: Overview!$D$10
Name Construction_Time: Overview!$D$28
Name Debt_Coverage_P50: Overview!$D$45
Name Debt_Coverage_P99: Overview!$D$46
Name Depreciation: Overview!$D$39
Name Insurance: Overview!$D$30
Name Interest_Rate: Overview!$D$48
Name Irradiation: Overview!$D$16
Name ITC_Percentage: Overview!$D$42
Name Land_Cost: Overview!$DF$26
Name Max_Debt: Debt!$B$2:$C$2
Name O_M: Overview!$D$31
Name O_M_Annual_Escalation: Overview!$D$36
Name Operating_Life: Overview!$D$12
Name Other: Overview!$D$35
Name Percentage_of_production_in_Year_1: Overview!$D$20
Name Placement_in_Service_Date: Overview!$D$11
Name PPA_Escalator: Overview!$D$23
Name PPA_Rate: Overview!$D$22
Name PPA_Term: Overview!$D$24
Name Project_Size_AC: Overview!$D$14
Name Project_Size_DC: Overview!$D$15
Name Property_Tax: Overview!$D$33
Name Site_Lease: Overview!$D$32
Name Site_Leaset_Annual_Escalation: Overview!$D$37
Name Tax_Rate: Overview!$D$41
Name Yield: Overview!$D$17

Sheet Table of Content
A1: ='Summary Inputs & Assumptions'!A2 -> STL Solar Model | C1: ='Summary Inputs & Assumptions'!A2 -> STL Solar Model
A2: ='Summary Inputs & Assumptions'!G16 -> Data Studies
A6: GENERAL INPUTS & ASSUMPTIONS
B7: OVERVIEW | D7: 2
B8: INFLUENCE CHART/MODEL FLOW | D8: 3
B9: SUMMARY INPUTS & ASSUMPTIONS | D9: 4
A11: CALCULATIONS
B12: FINANCIAL STATEMENTS | D12: 5
B13: DEBT SIZING | D13: 6
B14: CAPITAL CONTRIBUTIONS | D14: 7
A16: DATA
B17: EXTERNAL DATA
B18: ANALYSIS
A20: DASHBOARD
B21: GENERAL DASHBOARD
B22: SCENARIOS

Sheet Overview
P2: Labels
P3: User Input
C4: Problem Statement/Hyphotesis: | D4: STL Solar, is a startup solar energy developer planning a new solar project. STL Solar’s main objective is to maximize profit from the project. | P4: Fixed Text
C6: Logic &/ Formular: | D6: Net Profit: Revenue - Expenses; Revenue = Production x PPA Rate; Production = Size x Irradiation x Capacity Factor; DSCR = EBITDA / Debt Payment
B8: Input list | H8: Assumtions | L8: Known Decision Options/Solutions
B9: Input Name | C9: Input Type* | D9: Value** | E9: Data Variable Type*** | F9: Input/Data Source (if known) | H9: Description/Explation | I9: Related Input Variable if Any | J9: Value if Any | L9: # | M9: Input | N9: Discription/Explanation
B10: Construction Start Date | C10: Decision | D10: 44562 | E10: Date | F10: User | L10: 1 | M10: Depreciation | N10: Bonus Depreciation
B11: Placement in Service Date | C11: Decision | D11: 44727 | E11: Date | F11: User | L11: 2 | M11: PPA Rate | N11: Higher or lower than 0.058
B12: Operating Life | C12: Fixed | D12: 30 | E12: Number: Years | F12: User | H12: Duration project is expected to run | L12: 3 | M12: Depreciation | N12: MACRS
B14: Project Size (AC) | C14: Fixed | D14: 2 | E14: Number: MWac | F14: User
B15: Project Size (DC) | C15: Fixed | D15: =Project_Size_AC*1.36 -> 2.72 | E15: Number: MWdc | F15: User | H15: MWdc size of solar project
B16: Irradiation | D16: 1500 | E16: Number: kWh/m²/year | F16: User | H16: Estimated average annual sunlight
B17: Yield | C17: Fixed | D17: 1800 | E17: kWh/kWdc | F17: User
B18: Capacity Factor | C18: Drived/Fixed | D18: 0.85 | F18: Third Party | H18: Est. plant uptime efficiency
B19: Annual Degradation | C19: Fixed | D19: 0.003 | E19: Percentage | F19: User
B20: Percentage of production in Year 1 | C20: Fixed | D20: 1 | E20: Percentage | F20: User
B22: PPA Rate | C22: Decision | D22: 0.058 | E22: Currency: USD/kWh | F22: User | H22: Initial Power Purchase Agreement rate
B23: PPA Escalator | C23: Fixed | D23: 0 | E23: Percentage | F23: User
B24: PPA Term | C24: Fixed | D24: 15 | E24: Number: Years | F24: User
B26: Land Cost | C26: Fixed | D26: 1000000 | E26: Currency | F26: User
B27: All-in Development Cost | C27: Fixed | D27: 2.11 | E27: Number: $/Wdc
B28: Construction Time | C28: Fixed | D28: 12 | E28: Number: Months | F28: User | H28: Estimated construction duration
B30: Insurance | C30: Fixed | D30: 3200 | E30: Currency: USD/MWdc | F30: User/Client Database | H30: Insurance against common perils
B31: O&M | C31: Fixed | D31: 7500 | E31: Currency: USD/MWdc | F31: User/Client Database | H31: Operations and maintenance
B32: Site Lease | C32: Fixed | D32: 9500 | E32: Currency: USD/MWdc | F32: User/Client Database | H32: Site Lease
B33: Property Tax | C33: Fixed | D33: 6000 | E33: Currency: USD/MWdc | F33: User/Client Database | H33: Property Tax
B34: Asset Mgmt | C34: Fixed | D34: 5000 | E34: Currency: USD/MWdc | F34: User/Client Database | H34: Asset Management Fees
B35: Other | C35: Fixed | D35: 3000 | E35: Currency: USD/MWdc | F35: User/Client Database | H35: Misc cost = 3000 x Size
B36: O&M Annual Escalation | C36: Fixed | D36: 0.02 | E36: Percentage | F36: User | H36: % O&M grows by annually
B37: Site Leaset Annual Escalation | C37: Fixed | D37: 0.02 | E37: Percentage | F37: User | H37: % Site Lease grows by annually
B39: Depreciation | C39: Decision | D39: Bonus depreciation | E39: Text: Selection | F39: User | H39: 100% depreciation on CapEx in year 1
B41: Tax Rate | C41: Fixed | D41: 0.21 | E41: Percentage | F41: User
B42: ITC % | C42: Fixed | D42: 0.3 | E42: Percentage | F42: User
B43: PPC | C43: Fixed | D43: 1.1 | E43: Number | F43: User
B45: Debt Coverage P50 | C45: Fixed | D45: 1.5 | E45: Number | F45: User | H45: Debt Service Coverage Ratio required at P50
B46: Debt Coverage P99 | C46: Fixed | D46: 1 | E46: Number | F46: User | H46: Debt Service Coverage Ratio required at P99
B47: Amortization period | C47: Fixed | D47: 15 | E47: Number | F47: User | H47: Loan Term
B48: Swapped Interest Rate | C48: Fixed | D48: 0.05 | E48: Percentage | F48: User
B50: CO2 offset | C50: Fixed | D50: 0.9 | E50: Number: /MWh | F50: EPA | H50: Input to estimate carbon offset generated by project
A55: * | B55: Input Type (Decision/Fixed)
A56: ** | B56: Value (if known, if dataset leave blank)
A57: *** | B57: Data Variable Type Number, Date and Time, Text, Logical (boolean)

Sheet Influence Chart

Sheet Summary Inputs & Assumptions
A2: STL Solar Model
B5: Model Inputs & Tabs | I5: General Assumptions | O5: Dates | Q5: Year | R5: Quarter | S5: Month | T5: Date | W5: Description
B7: Inputs | F7: Formula/ Fixed Input | J7: Scenario | L7: P50 | P7: Start Date | Q7: =YEAR(T7) -> 2022 | R7: =ROUNDUP(MONTH(T7)/3,0) -> 1 | S7: =MONTH(T7) -> 1 | T7: =Construction_Start_Date -> 44562
B8: Inputs | F8: Manual Input | P8: Mechanical Completion Date | Q8: =YEAR(T8) -> 2022 | R8: =ROUNDUP(MONTH(T8)/3,0) -> 4 | S8: =MONTH(T8) -> 12 | T8: =DATE(Q7,S7+U10,1)-U8 -> 44913 | U8: 14 | V8: days
B9: Inputs | F9: Linked to Other Tabs | P9: Placement in Service Date | Q9: =YEAR(T9) -> 2023 | R9: =ROUNDUP(MONTH(T9)/3,0) -> 1 | S9: =MONTH(T9) -> 1 | T9: =T8+U9 -> 44927 | U9: 14 | V9: days
B10: Tabs | F10: Input Tab | P10: Substantial Completion Date | Q10: =YEAR(T10) -> 2023 | R10: =ROUNDUP(MONTH(T10)/3,0) -> 1 | S10: =MONTH(T10) -> 1 | T10: =DATE(Q7,S7+U10,1) -> 44927 | U10: =Construction_Time -> 12 | V10: Months
B11: Tabs | F11: Output Tab | P11: Final Completion Date | Q11: =YEAR(T11) -> 2023 | R11: =ROUNDUP(MONTH(T11)/3,0) -> 1 | S11: =MONTH(T11) -> 1 | T11: =T10+U11 -> 44941 | U11: 14 | V11: days (plus)
B13: Project Size (AC) | I13: Construction | O13: Funding Schedule | Q13: =Q5 -> Year | R13: =R5 -> Quarter | S13: =S5 -> Month | T13: =T5 -> Date | U13: % of TC capital funded | V13: % of Developer Capital Funded | W13: =W5 -> Description
B15: Project ID | G15: 00001 | J15: All-in Development Cost | K15: $/Wdc | L15: =All_in_Development_Cost -> 2.11 | P15: =P7 -> Start Date | Q15: =Q7 -> 2022 | R15: =R7 -> 1 | S15: =S7 -> 1 | T15: =T7 -> 44562 | U15: 0.01 | V15: 1
B16: Project Name | G16: Data Studies | J16: Cost Basis | L16: =+G19*L15*1000000 -> 5739200 | P16: =P8 -> Mechanical Completion Date | Q16: =Q8 -> 2022 | R16: =R8 -> 4 | S16: =S8 -> 12 | T16: =T8 -> 44913 | U16: 0.19
B17: Model period (Years) | J17: ITC % | L17: =ITC_Percentage -> 0.3 | P17: =P9 -> Placement in Service Date | Q17: =Q9 -> 2023 | R17: =R9 -> 1 | S17: =S9 -> 1 | T17: =T9 -> 44927
B18: Size (AC) | F18: MWac | G18: =Project_Size_AC -> 2 | J18: % of cost basis that is eligible for ITC | L18: 0.9 | P18: =P10 -> Substantial Completion Date | Q18: =Q10 -> 2023 | R18: =R10 -> 1 | S18: =S10 -> 1 | T18: =T10 -> 44927 | U18: 0.8
B19: Size (DC) | F19: MWdc | G19: =Project_Size_DC -> 2.72 | P19: =P11 -> Final Completion Date | Q19: =Q11 -> 2023 | R19: =R11 -> 1 | S19: =S11 -> 1 | T19: =T11 -> 44941
B21: Production | I21: Depreciation | O21: ='Capital Contribution Schedule'!B13 -> Contribution Schedule
P22: Year | Q22: Investor | R22: Developer | S22: ='Capital Contribution Schedule'!E13 -> Total
B23: Yield (kWh/kWdc) | E23: kWh/kWdc | F23: =Yield -> 1800 | J23: Depreciable Basis | L23: =IF(L24="Yes",L16-(L38*0.5),L16-(L38*0)) -> 4964408
B24: P50 Production (1st yr.) | E24: kWh | F24: =+F23*G19*1000 -> 4896000 | J24: Depreciate 100% in PIS Year (Bonus Dep) | L24: =IF(Depreciation="Bonus depreciation","Yes","No") -> Yes | P24: ='Capital Contribution Schedule'!B15 -> 2022 | Q24: ='Capital Contribution Schedule'!C15 -> 340908.48 | R24: ='Capital Contribution Schedule'!D15 -> 2429093.6 | S24: ='Capital Contribution Schedule'!E15 -> 2770002.1
B25: P99 as % of P50 | F25: 0.86 | P25: ='Capital Contribution Schedule'!B16 -> 2023 | Q25: ='Capital Contribution Schedule'!C16 -> 1363633.9 | R25: ='Capital Contribution Schedule'!D16 -> 0 | S25: ='Capital Contribution Schedule'!E16 -> 1363633.9
B26: P99 Production (1st yr.) | E26: kWh | F26: =+F24*F25 -> 4210560 | P26: ='Capital Contribution Schedule'!B17 -> 2024 | Q26: ='Capital Contribution Schedule'!C17 -> 0 | R26: ='Capital Contribution Schedule'!D17 -> 0 | S26: ='Capital Contribution Schedule'!E17 -> 0
B27: Percentage of production in Year 1 | F27: 1 | I27: MACRS | P27: ='Capital Contribution Schedule'!B18 -> 2025 | Q27: ='Capital Contribution Schedule'!C18 -> 0 | R27: ='Capital Contribution Schedule'!D18 -> 0 | S27: ='Capital Contribution Schedule'!E18 -> 0
B28: Annual Degradation | F28: =Annual_Degradation -> 0.003 | J28: Year | L28: % | P28: ='Capital Contribution Schedule'!B19 -> 2026 | Q28: ='Capital Contribution Schedule'!C19 -> 0 | R28: ='Capital Contribution Schedule'!D19 -> 0 | S28: ='Capital Contribution Schedule'!E19 -> 0
B29: PPA Price | E29: Cents / kWh | F29: =PPA_Rate -> 0.058 | J29: 1 | L29: 0.05 | P29: ='Capital Contribution Schedule'!B20 -> 2027 | Q29: ='Capital Contribution Schedule'!C20 -> 0 | R29: ='Capital Contribution Schedule'!D20 -> 0 | S29: ='Capital Contribution Schedule'!E20 -> 0
B30: PPA Escalator | F30: 0 | J30: 2 | L30: 0.38 | P30: ='Capital Contribution Schedule'!B21 -> 2028 | Q30: ='Capital Contribution Schedule'!C21 -> 0 | R30: ='Capital Contribution Schedule'!D21 -> 0 | S30: ='Capital Contribution Schedule'!E21 -> 0
B31: PPA Term | E31: years | F31: =PPA_Term -> 15 | J31: 3 | L31: 0.228 | P31: ='Capital Contribution Schedule'!B22 -> 2029 | Q31: ='Capital Contribution Schedule'!C22 -> 0 | R31: ='Capital Contribution Schedule'!D22 -> 0 | S31: ='Capital Contribution Schedule'!E22 -> 0
J32: 4 | L32: 0.1368 | P32: ='Capital Contribution Schedule'!B23 -> 2030 | Q32: ='Capital Contribution Schedule'!C23 -> 0 | R32: ='Capital Contribution Schedule'!D23 -> 0 | S32: ='Capital Contribution Schedule'!E23 -> 0
J33: 5 | L33: 0.1094 | P33: ='Capital Contribution Schedule'!B24 -> 2031 | Q33: ='Capital Contribution Schedule'!C24 -> 0 | R33: ='Capital Contribution Schedule'!D24 -> 0 | S33: ='Capital Contribution Schedule'!E24 -> 0
J34: 6 | L34: 0.0958 | P34: ='Capital Contribution Schedule'!B25 -> 2032 | Q34: ='Capital Contribution Schedule'!C25 -> 0 | R34: ='Capital Contribution Schedule'!D25 -> 0 | S34: ='Capital Contribution Schedule'!E25 -> 0
B37: Operating Expenses | F37: Escalation | G37: % / yr | I37: Tax Equity | O37: Debt Sizing
I38: ITC Amount | L38: =+G19*L15*L17*L18*1000000 -> 1549584 | O38: Swapped Interest Rate | Q38: =Interest_Rate -> 0.05 | R38: all-in fixed for 15 years (includes loan margin)
B39: Insurance | D39: =Insurance -> 3200 | E39: $/MWdc/yr. | F39: flat | G39: 0 | I39: PPC | L39: 1.1 | O39: P50 DSCR | Q39: =Debt_Coverage_P50 -> 1.5
B40: O&M | D40: =O_M -> 7500 | E40: $/MWdc/yr. | F40: escalates | G40: 0.02 | I40: Investment Term years | L40: 5 | O40: P99 DSCR | Q40: =Debt_Coverage_P99 -> 1
B41: Site Lease | D41: =Site_Lease -> 9500 | E41: $/MWdc/yr. | F41: escalates | G41: 0.02 | I41: ITC Investor Ownership % | L41: 0.99 | O41: Amortization period | Q41: =PPA_Term -> 15 | R41: years
B42: Property Tax | D42: =Property_Tax -> 6000 | E42: $/MWdc/yr. | F42: flat | G42: 0 | I42: Call % of ITC Equity | L42: 0.05 | O42: Term Loan Size | Q42: =Debt!C2 -> 1605564 | R42: $ in actual
B43: Asset Management | D43: =Asset_Mgmt -> 5000 | E43: $/MWdc/yr. | F43: flat | G43: 0 | I43: Partnership Flip Yes/No | L43: Yes
B44: Other | D44: =Other -> 3000 | E44: $/MWdc/yr. | F44: flat | G44: 0 | I44: Tax Rate | L44: =Tax_Rate -> 0.21
I45: Exit Date | L45: =DATE(YEAR(T9)+L40,MONTH(3),31) -> 46783

Sheet Financial Statements
B1: PPA Scenerio
B2: ='Summary Inputs & Assumptions'!L7 -> P50
B3: Income Statement
D5: 1 | E5: 2 | F5: 3 | G5: 4 | H5: 5 | I5: 6 | J5: 7 | K5: 8 | L5: 9 | M5: 10 | N5: 11 | O5: 12 | P5: 13 | Q5: 14 | R5: 15 | S5: 16 | T5: 17 | U5: 18 | V5: 19 | W5: 20 | X5: 21 | Y5: 22 | Z5: 23 | AA5: 24 | AB5: 25 | AC5: 26 | AD5: 27 | AE5: 28 | AF5: 29 | AG5: 30
C6: Year | D6: =YEAR('Summary Inputs & Assumptions'!T7) -> 2022 | E6: =IF(E5>'Summary Inputs & Assumptions'!$Q$41,0,D6+1) -> 2023 | F6: =IF(F5>'Summary Inputs & Assumptions'!$Q$41,0,E6+1) -> 2024 | G6: =IF(G5>'Summary Inputs & Assumptions'!$Q$41,0,F6+1) -> 2025 | H6: =IF(H5>'Summary Inputs & Assumptions'!$Q$41,0,G6+1) -> 2026 | I6: =IF(I5>'Summary Inputs & Assumptions'!$Q$41,0,H6+1) -> 2027 | J6: =IF(J5>'Summary Inputs & Assumptions'!$Q$41,0,I6+1) -> 2028 | K6: =IF(K5>'Summary Inputs & Assumptions'!$Q$41,0,J6+1) -> 2029 | L6: =IF(L5>'Summary Inputs & Assumptions'!$Q$41,0,K6+1) -> 2030 | ... AG6: =IF(AG5>'Summary Inputs & Assumptions'!$Q$41,0,AF6+1) -> 0
B8: Power Purchase Agreement Revenues
C9: ='Summary Inputs & Assumptions'!B19 -> Size (DC) | D9: =Project_Size_DC -> 2.72 | E9: =Project_Size_DC -> 2.72 | F9: =Project_Size_DC -> 2.72 | G9: =Project_Size_DC -> 2.72 | H9: =Project_Size_DC -> 2.72 | I9: =Project_Size_DC -> 2.72 | J9: =Project_Size_DC -> 2.72 | K9: =Project_Size_DC -> 2.72 | ... AG9: =Project_Size_DC -> 2.72
C10: ='Summary Inputs & Assumptions'!B23 -> Yield (kWh/kWdc) | D10: =Yield -> 1800 | E10: =Yield -> 1800 | F10: =Yield -> 1800 | G10: =Yield -> 1800 | H10: =Yield -> 1800 | I10: =Yield -> 1800 | J10: =Yield -> 1800 | K10: =Yield -> 1800 | ... AG10: =Yield -> 1800
C11: ='Summary Inputs & Assumptions'!B27 -> Percentage of production in Year 1 | D11: =IF(D$6=YEAR(Construction_Start_Date),Percentage_of_production_in_Year_1,C11*(1-Annual_Degradation)) -> 1 | E11: =IF(E$6=YEAR(Construction_Start_Date),Percentage_of_production_in_Year_1,D11*(1-Annual_Degradation)) -> 0.997 | F11: =IF(F$6=YEAR(Construction_Start_Date),Percentage_of_production_in_Year_1,E11*(1-Annual_Degradation)) -> 0.994009 | G11: =IF(G$6=YEAR(Construction_Start_Date),Percentage_of_production_in_Year_1,F11*(1-Annual_Degradation)) -> 0.99102697 | H11: =IF(H$6=YEAR(Construction_Start_Date),Percentage_of_production_in_Year_1,G11*(1-Annual_Degradation)) -> 0.98805389 | I11: =IF(I$6=YEAR(Construction_Start_Date),Percentage_of_production_in_Year_1,H11*(1-Annual_Degradation)) -> 0.98508973 | J11: =IF(J$6=YEAR(Construction_Start_Date),Percentage_of_production_in_Year_1,I11*(1-Annual_Degradation)) -> 0.98213446 | K11: =IF(K$6=YEAR(Construction_Start_Date),Percentage_of_production_in_Year_1,J11*(1-Annual_Degradation)) -> 0.97918806 | ... AG11: =IF(AG$6=YEAR(Construction_Start_Date),Percentage_of_production_in_Year_1,AF11*(1-Annual_Degradation)) -> 0.91655724
C12: ='Summary Inputs & Assumptions'!B29 -> PPA Price | D12: =IF(D$6=YEAR(Construction_Start_Date),PPA_Rate*(1+PPA_Escalator),C12*(1+PPA_Escalator)) -> 0.058 | E12: =IF(E$6=YEAR(Construction_Start_Date),PPA_Rate*(1+PPA_Escalator),D12*(1+PPA_Escalator)) -> 0.058 | F12: =IF(F$6=YEAR(Construction_Start_Date),PPA_Rate*(1+PPA_Escalator),E12*(1+PPA_Escalator)) -> 0.058 | G12: =IF(G$6=YEAR(Construction_Start_Date),PPA_Rate*(1+PPA_Escalator),F12*(1+PPA_Escalator)) -> 0.058 | H12: =IF(H$6=YEAR(Construction_Start_Date),PPA_Rate*(1+PPA_Escalator),G12*(1+PPA_Escalator)) -> 0.058 | I12: =IF(I$6=YEAR(Construction_Start_Date),PPA_Rate*(1+PPA_Escalator),H12*(1+PPA_Escalator)) -> 0.058 | J12: =IF(J$6=YEAR(Construction_Start_Date),PPA_Rate*(1+PPA_Escalator),I12*(1+PPA_Escalator)) -> 0.058 | K12: =IF(K$6=YEAR(Construction_Start_Date),PPA_Rate*(1+PPA_Escalator),J12*(1+PPA_Escalator)) -> 0.058 | ... AG12: =IF(AG$6=YEAR(Construction_Start_Date),PPA_Rate*(1+PPA_Escalator),AF12*(1+PPA_Escalator)) -> 0.058
C13: Period (1 = full, <1 = Partial) | D13: =IF(D6=YEAR(Placement_in_Service_Date),((DATE(YEAR(Placement_in_Service_Date),12,31))-Placement_in_Service_Date+1)/((DATE(YEAR(Placement_in_Service_Date),12,31))-(DATE(YEAR(Placement_in_Service_Date),1,1))+1),IF(D6<YEAR(Placement_in_Service_Date),0,1)) -> 0.54794521 | E13: =IF(E6=YEAR(Placement_in_Service_Date),((DATE(YEAR(Placement_in_Service_Date),12,31))-Placement_in_Service_Date+1)/((DATE(YEAR(Placement_in_Service_Date),12,31))-(DATE(YEAR(Placement_in_Service_Date),1,1))+1),IF(E6<YEAR(Placement_in_Service_Date),0,1)) -> 1 | F13: =IF(F6=YEAR(Placement_in_Service_Date),((DATE(YEAR(Placement_in_Service_Date),12,31))-Placement_in_Service_Date+1)/((DATE(YEAR(Placement_in_Service_Date),12,31))-(DATE(YEAR(Placement_in_Service_Date),1,1))+1),IF(F6<YEAR(Placement_in_Service_Date),0,1)) -> 1 | G13: =IF(G6=YEAR(Placement_in_Service_Date),((DATE(YEAR(Placement_in_Service_Date),12,31))-Placement_in_Service_Date+1)/((DATE(YEAR(Placement_in_Service_Date),12,31))-(DATE(YEAR(Placement_in_Service_Date),1,1))+1),IF(G6<YEAR(Placement_in_Service_Date),0,1)) -> 1 | H13: =IF(H6=YEAR(Placement_in_Service_Date),((DATE(YEAR(Placement_in_Service_Date),12,31))-Placement_in_Service_Date+1)/((DATE(YEAR(Placement_in_Service_Date),12,31))-(DATE(YEAR(Placement_in_Service_Date),1,1))+1),IF(H6<YEAR(Placement_in_Service_Date),0,1)) -> 1 | I13: =IF(I6=YEAR(Placement_in_Service_Date),((DATE(YEAR(Placement_in_Service_Date),12,31))-Placement_in_Service_Date+1)/((DATE(YEAR(Placement_in_Service_Date),12,31))-(DATE(YEAR(Placement_in_Service_Date),1,1))+1),IF(I6<YEAR(Placement_in_Service_Date),0,1)) -> 1 | J13: =IF(J6=YEAR(Placement_in_Service_Date),((DATE(YEAR(Placement_in_Service_Date),12,31))-Placement_in_Service_Date+1)/((DATE(YEAR(Placement_in_Service_Date),12,31))-(DATE(YEAR(Placement_in_Service_Date),1,1))+1),IF(J6<YEAR(Placement_in_Service_Date),0,1)) -> 1 | K13: =IF(K6=YEAR(Placement_in_Service_Date),((DATE(YEAR(Placement_in_Service_Date),12,31))-Placement_in_Service_Date+1)/((DATE(YEAR(Placement_in_Service_Date),12,31))-(DATE(YEAR(Placement_in_Service_Date),1,1))+1),IF(K6<YEAR(Placement_in_Service_Date),0,1)) -> 1 | ... AG13: =IF(AG6=YEAR(Placement_in_Service_Date),((DATE(YEAR(Placement_in_Service_Date),12,31))-Placement_in_Service_Date+1)/((DATE(YEAR(Placement_in_Service_Date),12,31))-(DATE(YEAR(Placement_in_Service_Date),1,1))+1),IF(AG6<YEAR(Placement_in_Service_Date),0,1)) -> 0
C15: P50 Revenue | D15: =D9*D10*D11*D12*1000*D13 -> 155598.9 | E15: =E9*E10*E11*E12*1000*E13 -> 283116.1 | F15: =F9*F10*F11*F12*1000*F13 -> 282266.75 | G15: =G9*G10*G11*G12*1000*G13 -> 281419.95 | H15: =H9*H10*H11*H12*1000*H13 -> 280575.69 | I15: =I9*I10*I11*I12*1000*I13 -> 279733.96 | J15: =J9*J10*J11*J12*1000*J13 -> 278894.76 | K15: =K9*K10*K11*K12*1000*K13 -> 278058.07 | ... AG15: =AG9*AG10*AG11*AG12*1000*AG13 -> 0
B17: ='Summary Inputs & Assumptions'!B37 -> Operating Expenses
C18: ='Summary Inputs & Assumptions'!B39 -> Insurance | D18: =IF(AND(D$6=YEAR(Construction_Start_Date),D$5<Debt!$C$3),'Summary Inputs & Assumptions'!$D$39*D$13,IF(D$5>'Summary Inputs & Assumptions'!$Q$41,0,(C18*(1+'Summary Inputs & Assumptions'!$G39)))) -> 1753.4247 | E18: =IF(AND(E$6=YEAR('Summary Inputs & Assumptions'!$T$7),E$5<Debt!$C$3),'Summary Inputs & Assumptions'!E39*E$13,IF(E$5>'Summary Inputs & Assumptions'!$Q$41,0,(D18/D$13)*(1+'Summary Inputs & Assumptions'!$G39))) -> 3200 | F18: =IF(AND(F$6=YEAR('Summary Inputs & Assumptions'!$T$7),F$5<Debt!$C$3),'Summary Inputs & Assumptions'!F39*F$13,IF(F$5>'Summary Inputs & Assumptions'!$Q$41,0,(E18/E$13)*(1+'Summary Inputs & Assumptions'!$G39))) -> 3200 | G18: =IF(AND(G$6=YEAR('Summary Inputs & Assumptions'!$T$7),G$5<Debt!$C$3),'Summary Inputs & Assumptions'!G39*G$13,IF(G$5>'Summary Inputs & Assumptions'!$Q$41,0,(F18/F$13)*(1+'Summary Inputs & Assumptions'!$G39))) -> 3200 | H18: =IF(AND(H$6=YEAR('Summary Inputs & Assumptions'!$T$7),H$5<Debt!$C$3),'Summary Inputs & Assumptions'!#REF!*H$13,IF(H$5>'Summary Inputs & Assumptions'!$Q$41,0,(G18/G$13)*(1+'Summary Inputs & Assumptions'!$G39))) -> 3200 | I18: =IF(AND(I$6=YEAR('Summary Inputs & Assumptions'!$T$7),I$5<Debt!$C$3),'Summary Inputs & Assumptions'!#REF!*I$13,IF(I$5>'Summary Inputs & Assumptions'!$Q$41,0,(H18/H$13)*(1+'Summary Inputs & Assumptions'!$G39))) -> 3200 | J18: =IF(AND(J$6=YEAR('Summary Inputs & Assumptions'!$T$7),J$5<Debt!$C$3),'Summary Inputs & Assumptions'!#REF!*J$13,IF(J$5>'Summary Inputs & Assumptions'!$Q$41,0,(I18/I$13)*(1+'Summary Inputs & Assumptions'!$G39))) -> 3200 | K18: =IF(AND(K$6=YEAR('Summary Inputs & Assumptions'!$T$7),K$5<Debt!$C$3),'Summary Inputs & Assumptions'!#REF!*K$13,IF(K$5>'Summary Inputs & Assumptions'!$Q$41,0,(J18/J$13)*(1+'Summary Inputs & Assumptions'!$G39))) -> 3200 | L18: =IF(AND(L$6=YEAR('Summary Inputs & Assumptions'!$T$7),L$5<Debt!$C$3),'Summary Inputs & Assumptions'!#REF!*L$13,IF(L$5>'Summary Inputs & Assumptions'!$Q$41,0,(K18/K$13)*(1+'Summary Inputs & Assumptions'!$G39))) -> 3200 | M18: =IF(AND(M$6=YEAR('Summary Inputs & Assumptions'!$T$7),M$5<Debt!$C$3),'Summary Inputs & Assumptions'!#REF!*M$13,IF(M$5>'Summary Inputs & Assumptions'!$Q$41,0,(L18/L$13)*(1+'Summary Inputs & Assumptions'!$G39))) -> 3200 | N18: =IF(AND(N$6=YEAR('Summary Inputs & Assumptions'!$T$7),N$5<Debt!$C$3),'Summary Inputs & Assumptions'!#REF!*N$13,IF(N$5>'Summary Inputs & Assumptions'!$Q$41,0,(M18/M$13)*(1+'Summary Inputs & Assumptions'!$G39))) -> 3200 | O18: =IF(AND(O$6=YEAR('Summary Inputs & Assumptions'!$T$7),O$5<Debt!$C$3),'Summary Inputs & Assumptions'!#REF!*O$13,IF(O$5>'Summary Inputs & Assumptions'!$Q$41,0,(N18/N$13)*(1+'Summary Inputs & Assumptions'!$G39))) -> 3200 | ... R18: =IF(AND(R$6=YEAR('Summary Inputs & Assumptions'!$T$7),R$5<Debt!$C$3),'Summary Inputs & Assumptions'!#REF!*R$13,IF(R$5>'Summary Inputs & Assumptions'!$Q$41,0,(Q18/Q$13)*(1+'Summary Inputs & Assumptions'!$G39))) -> 3200 | S18: =IF(AND(S$6=YEAR('Summary Inputs & Assumptions'!$T$7),S$5<Debt!$C$3),'Summary Inputs & Assumptions'!V62*S$13,IF(S$5>'Summary Inputs & Assumptions'!$Q$41,0,(R18/R$13)*(1+'Summary Inputs & Assumptions'!$G39))) -> 0 | T18: =IF(AND(T$6=YEAR('Summary Inputs & Assumptions'!$T$7),T$5<Debt!$C$3),'Summary Inputs & Assumptions'!W62*T$13,IF(T$5>'Summary Inputs & Assumptions'!$Q$41,0,(S18/S$13)*(1+'Summary Inputs & Assumptions'!$G39))) -> 0 | U18: =IF(AND(U$6=YEAR('Summary Inputs & Assumptions'!$T$7),U$5<Debt!$C$3),'Summary Inputs & Assumptions'!X62*U$13,IF(U$5>'Summary Inputs & Assumptions'!$Q$41,0,(T18/T$13)*(1+'Summary Inputs & Assumptions'!$G39))) -> 0 | V18: =IF(AND(V$6=YEAR('Summary Inputs & Assumptions'!$T$7),V$5<Debt!$C$3),'Summary Inputs & Assumptions'!Y62*V$13,IF(V$5>'Summary Inputs & Assumptions'!$Q$41,0,(U18/U$13)*(1+'Summary Inputs & Assumptions'!$G39))) -> 0 | W18: =IF(AND(W$6=YEAR('Summary Inputs & Assumptions'!$T$7),W$5<Debt!$C$3),'Summary Inputs & Assumptions'!Z62*W$13,IF(W$5>'Summary Inputs & Assumptions'!$Q$41,0,(V18/V$13)*(1+'Summary Inputs & Assumptions'!$G39))) -> 0 | X18: =IF(AND(X$6=YEAR('Summary Inputs & Assumptions'!$T$7),X$5<Debt!$C$3),'Summary Inputs & Assumptions'!AA60*X$13,IF(X$5>'Summary Inputs & Assumptions'!$Q$41,0,(W18/W$13)*(1+'Summary Inputs & Assumptions'!$G39))) -> 0 | Y18: =IF(AND(Y$6=YEAR('Summary Inputs & Assumptions'!$T$7),Y$5<Debt!$C$3),'Summary Inputs & Assumptions'!#REF!*Y$13,IF(Y$5>'Summary Inputs & Assumptions'!$Q$41,0,(X18/X$13)*(1+'Summary Inputs & Assumptions'!$G39))) -> 0 | Z18: =IF(AND(Z$6=YEAR('Summary Inputs & Assumptions'!$T$7),Z$5<Debt!$C$3),'Summary Inputs & Assumptions'!#REF!*Z$13,IF(Z$5>'Summary Inputs & Assumptions'!$Q$41,0,(Y18/Y$13)*(1+'Summary Inputs & Assumptions'!$G39))) -> 0 | AA18: =IF(AND(AA$6=YEAR('Summary Inputs & Assumptions'!$T$7),AA$5<Debt!$C$3),'Summary Inputs & Assumptions'!#REF!*AA$13,IF(AA$5>'Summary Inputs & Assumptions'!$Q$41,0,(Z18/Z$13)*(1+'Summary Inputs & Assumptions'!$G39))) -> 0 | AB18: =IF(AND(AB$6=YEAR('Summary Inputs & Assumptions'!$T$7),AB$5<Debt!$C$3),'Summary Inputs & Assumptions'!AB60*AB$13,IF(AB$5>'Summary Inputs & Assumptions'!$Q$41,0,(AA18/AA$13)*(1+'Summary Inputs & Assumptions'!$G39))) -> 0 | AC18: =IF(AND(AC$6=YEAR('Summary Inputs & Assumptions'!$T$7),AC$5<Debt!$C$3),'Summary Inputs & Assumptions'!AC60*AC$13,IF(AC$5>'Summary Inputs & Assumptions'!$Q$41,0,(AB18/AB$13)*(1+'Summary Inputs & Assumptions'!$G39))) -> 0 | AD18: =IF(AND(AD$6=YEAR('Summary Inputs & Assumptions'!$T$7),AD$5<Debt!$C$3),'Summary Inputs & Assumptions'!AD60*AD$13,IF(AD$5>'Summary Inputs & Assumptions'!$Q$41,0,(AC18/AC$13)*(1+'Summary Inputs & Assumptions'!$G39))) -> 0 | AE18: =IF(AND(AE$6=YEAR('Summary Inputs & Assumptions'!$T$7),AE$5<Debt!$C$3),'Summary Inputs & Assumptions'!AE60*AE$13,IF(AE$5>'Summary Inputs & Assumptions'!$Q$41,0,(AD18/AD$13)*(1+'Summary Inputs & Assumptions'!$G39))) -> 0 | AF18: =IF(AND(AF$6=YEAR('Summary Inputs & Assumptions'!$T$7),AF$5<Debt!$C$3),'Summary Inputs & Assumptions'!AF60*AF$13,IF(AF$5>'Summary Inputs & Assumptions'!$Q$41,0,(AE18/AE$13)*(1+'Summary Inputs & Assumptions'!$G39))) -> 0 | AG18: =IF(AND(AG$6=YEAR('Summary Inputs & Assumptions'!$T$7),AG$5<Debt!$C$3),'Summary Inputs & Assumptions'!AG60*AG$13,IF(AG$5>'Summary Inputs & Assumptions'!$Q$41,0,(AF18/AF$13)*(1+'Summary Inputs & Assumptions'!$G39))) -> 0
C19: ='Summary Inputs & Assumptions'!B40 -> O&M | D19: =IF(AND(D$6=YEAR('Summary Inputs & Assumptions'!$T$7),D$5<Debt!$C$3),'Summary Inputs & Assumptions'!$D$40*D$13,IF(D$5>'Summary Inputs & Assumptions'!$Q$41,0,(C19*(1+'Summary Inputs & Assumptions'!$G40)))) -> 4109.589 | E19: =IF(AND(E$6=YEAR('Summary Inputs & Assumptions'!$T$7),E$5<Debt!$C$3),'Summary Inputs & Assumptions'!E40*E$13,IF(E$5>'Summary Inputs & Assumptions'!$Q$41,0,(D19/D$13)*(1+'Summary Inputs & Assumptions'!$G40))) -> 7650 | F19: =IF(AND(F$6=YEAR('Summary Inputs & Assumptions'!$T$7),F$5<Debt!$C$3),'Summary Inputs & Assumptions'!F40*F$13,IF(F$5>'Summary Inputs & Assumptions'!$Q$41,0,(E19/E$13)*(1+'Summary Inputs & Assumptions'!$G40))) -> 7803 | G19: =IF(AND(G$6=YEAR('Summary Inputs & Assumptions'!$T$7),G$5<Debt!$C$3),'Summary Inputs & Assumptions'!G40*G$13,IF(G$5>'Summary Inputs & Assumptions'!$Q$41,0,(F19/F$13)*(1+'Summary Inputs & Assumptions'!$G40))) -> 7959.06 | H19: =IF(AND(H$6=YEAR('Summary Inputs & Assumptions'!$T$7),H$5<Debt!$C$3),'Summary Inputs & Assumptions'!#REF!*H$13,IF(H$5>'Summary Inputs & Assumptions'!$Q$41,0,(G19/G$13)*(1+'Summary Inputs & Assumptions'!$G40))) -> 8118.2412 | I19: =IF(AND(I$6=YEAR('Summary Inputs & Assumptions'!$T$7),I$5<Debt!$C$3),'Summary Inputs & Assumptions'!#REF!*I$13,IF(I$5>'Summary Inputs & Assumptions'!$Q$41,0,(H19/H$13)*(1+'Summary Inputs & Assumptions'!$G40))) -> 8280.606 | J19: =IF(AND(J$6=YEAR('Summary Inputs & Assumptions'!$T$7),J$5<Debt!$C$3),'Summary Inputs & Assumptions'!#REF!*J$13,IF(J$5>'Summary Inputs & Assumptions'!$Q$41,0,(I19/I$13)*(1+'Summary Inputs & Assumptions'!$G40))) -> 8446.2181 | K19: =IF(AND(K$6=YEAR('Summary Inputs & Assumptions'!$T$7),K$5<Debt!$C$3),'Summary Inputs & Assumptions'!#REF!*K$13,IF(K$5>'Summary Inputs & Assumptions'!$Q$41,0,(J19/J$13)*(1+'Summary Inputs & Assumptions'!$G40))) -> 8615.1425 | L19: =IF(AND(L$6=YEAR('Summary Inputs & Assumptions'!$T$7),L$5<Debt!$C$3),'Summary Inputs & Assumptions'!#REF!*L$13,IF(L$5>'Summary Inputs & Assumptions'!$Q$41,0,(K19/K$13)*(1+'Summary Inputs & Assumptions'!$G40))) -> 8787.4454 | M19: =IF(AND(M$6=YEAR('Summary Inputs & Assumptions'!$T$7),M$5<Debt!$C$3),'Summary Inputs & Assumptions'!#REF!*M$13,IF(M$5>'Summary Inputs & Assumptions'!$Q$41,0,(L19/L$13)*(1+'Summary Inputs & Assumptions'!$G40))) -> 8963.1943 | N19: =IF(AND(N$6=YEAR('Summary Inputs & Assumptions'!$T$7),N$5<Debt!$C$3),'Summary Inputs & Assumptions'!#REF!*N$13,IF(N$5>'Summary Inputs & Assumptions'!$Q$41,0,(M19/M$13)*(1+'Summary Inputs & Assumptions'!$G40))) -> 9142.4581 | O19: =IF(AND(O$6=YEAR('Summary Inputs & Assumptions'!$T$7),O$5<Debt!$C$3),'Summary Inputs & Assumptions'!#REF!*O$13,IF(O$5>'Summary Inputs & Assumptions'!$Q$41,0,(N19/N$13)*(1+'Summary Inputs & Assumptions'!$G40))) -> 9325.3073 | ... AG19: =IF(AND(AG$6=YEAR('Summary Inputs & Assumptions'!$T$7),AG$5<Debt!$C$3),'Summary Inputs & Assumptions'!#REF!*AG$13,IF(AG$5>'Summary Inputs & Assumptions'!$Q$41,0,(AF19/AF$13)*(1+'Summary Inputs & Assumptions'!$G40))) -> 0
C20: ='Summary Inputs & Assumptions'!B41 -> Site Lease | D20: =IF(AND(D$6=YEAR('Summary Inputs & Assumptions'!$T$7),D$5<Debt!$C$3),'Summary Inputs & Assumptions'!$D$41*D$13,IF(D$5>'Summary Inputs & Assumptions'!$Q$41,0,(C20*(1+'Summary Inputs & Assumptions'!$G41)))) -> 5205.4795 | E20: =IF(AND(E$6=YEAR('Summary Inputs & Assumptions'!$T$7),E$5<Debt!$C$3),'Summary Inputs & Assumptions'!E41*E$13,IF(E$5>'Summary Inputs & Assumptions'!$Q$41,0,(D20/D$13)*(1+'Summary Inputs & Assumptions'!$G41))) -> 9690 | F20: =IF(AND(F$6=YEAR('Summary Inputs & Assumptions'!$T$7),F$5<Debt!$C$3),'Summary Inputs & Assumptions'!F41*F$13,IF(F$5>'Summary Inputs & Assumptions'!$Q$41,0,(E20/E$13)*(1+'Summary Inputs & Assumptions'!$G41))) -> 9883.8 | G20: =IF(AND(G$6=YEAR('Summary Inputs & Assumptions'!$T$7),G$5<Debt!$C$3),'Summary Inputs & Assumptions'!G41*G$13,IF(G$5>'Summary Inputs & Assumptions'!$Q$41,0,(F20/F$13)*(1+'Summary Inputs & Assumptions'!$G41))) -> 10081.476 | H20: =IF(AND(H$6=YEAR('Summary Inputs & Assumptions'!$T$7),H$5<Debt!$C$3),'Summary Inputs & Assumptions'!#REF!*H$13,IF(H$5>'Summary Inputs & Assumptions'!$Q$41,0,(G20/G$13)*(1+'Summary Inputs & Assumptions'!$G41))) -> 10283.106 | I20: =IF(AND(I$6=YEAR('Summary Inputs & Assumptions'!$T$7),I$5<Debt!$C$3),'Summary Inputs & Assumptions'!#REF!*I$13,IF(I$5>'Summary Inputs & Assumptions'!$Q$41,0,(H20/H$13)*(1+'Summary Inputs & Assumptions'!$G41))) -> 10488.768 | J20: =IF(AND(J$6=YEAR('Summary Inputs & Assumptions'!$T$7),J$5<Debt!$C$3),'Summary Inputs & Assumptions'!#REF!*J$13,IF(J$5>'Summary Inputs & Assumptions'!$Q$41,0,(I20/I$13)*(1+'Summary Inputs & Assumptions'!$G41))) -> 10698.543 | K20: =IF(AND(K$6=YEAR('Summary Inputs & Assumptions'!$T$7),K$5<Debt!$C$3),'Summary Inputs & Assumptions'!#REF!*K$13,IF(K$5>'Summary Inputs & Assumptions'!$Q$41,0,(J20/J$13)*(1+'Summary Inputs & Assumptions'!$G41))) -> 10912.514 | L20: =IF(AND(L$6=YEAR('Summary Inputs & Assumptions'!$T$7),L$5<Debt!$C$3),'Summary Inputs & Assumptions'!#REF!*L$13,IF(L$5>'Summary Inputs & Assumptions'!$Q$41,0,(K20/K$13)*(1+'Summary Inputs & Assumptions'!$G41))) -> 11130.764 | M20: =IF(AND(M$6=YEAR('Summary Inputs & Assumptions'!$T$7),M$5<Debt!$C$3),'Summary Inputs & Assumptions'!#REF!*M$13,IF(M$5>'Summary Inputs & Assumptions'!$Q$41,0,(L20/L$13)*(1+'Summary Inputs & Assumptions'!$G41))) -> 11353.379 | N20: =IF(AND(N$6=YEAR('Summary Inputs & Assumptions'!$T$7),N$5<Debt!$C$3),'Summary Inputs & Assumptions'!#REF!*N$13,IF(N$5>'Summary Inputs & Assumptions'!$Q$41,0,(M20/M$13)*(1+'Summary Inputs & Assumptions'!$G41))) -> 11580.447 | O20: =IF(AND(O$6=YEAR('Summary Inputs & Assumptions'!$T$7),O$5<Debt!$C$3),'Summary Inputs & Assumptions'!#REF!*O$13,IF(O$5>'Summary Inputs & Assumptions'!$Q$41,0,(N20/N$13)*(1+'Summary Inputs & Assumptions'!$G41))) -> 11812.056 | ... AG20: =IF(AND(AG$6=YEAR('Summary Inputs & Assumptions'!$T$7),AG$5<Debt!$C$3),'Summary Inputs & Assumptions'!#REF!*AG$13,IF(AG$5>'Summary Inputs & Assumptions'!$Q$41,0,(AF20/AF$13)*(1+'Summary Inputs & Assumptions'!$G41))) -> 0
C21: ='Summary Inputs & Assumptions'!B42 -> Property Tax | D21: =IF(AND(D$6=YEAR('Summary Inputs & Assumptions'!$T$7),D$5<Debt!$C$3),'Summary Inputs & Assumptions'!$D$42*D$13,IF(D$5>'Summary Inputs & Assumptions'!$Q$41,0,(C21*(1+'Summary Inputs & Assumptions'!$G42)))) -> 3287.6712 | E21: =IF(AND(E$6=YEAR('Summary Inputs & Assumptions'!$T$7),E$5<Debt!$C$3),'Summary Inputs & Assumptions'!E42*E$13,IF(E$5>'Summary Inputs & Assumptions'!$Q$41,0,(D21/D$13)*(1+'Summary Inputs & Assumptions'!$G42))) -> 6000 | F21: =IF(AND(F$6=YEAR('Summary Inputs & Assumptions'!$T$7),F$5<Debt!$C$3),'Summary Inputs & Assumptions'!F42*F$13,IF(F$5>'Summary Inputs & Assumptions'!$Q$41,0,(E21/E$13)*(1+'Summary Inputs & Assumptions'!$G42))) -> 6000 | G21: =IF(AND(G$6=YEAR('Summary Inputs & Assumptions'!$T$7),G$5<Debt!$C$3),'Summary Inputs & Assumptions'!G42*G$13,IF(G$5>'Summary Inputs & Assumptions'!$Q$41,0,(F21/F$13)*(1+'Summary Inputs & Assumptions'!$G42))) -> 6000 | H21: =IF(AND(H$6=YEAR('Summary Inputs & Assumptions'!$T$7),H$5<Debt!$C$3),'Summary Inputs & Assumptions'!#REF!*H$13,IF(H$5>'Summary Inputs & Assumptions'!$Q$41,0,(G21/G$13)*(1+'Summary Inputs & Assumptions'!$G42))) -> 6000 | I21: =IF(AND(I$6=YEAR('Summary Inputs & Assumptions'!$T$7),I$5<Debt!$C$3),'Summary Inputs & Assumptions'!#REF!*I$13,IF(I$5>'Summary Inputs & Assumptions'!$Q$41,0,(H21/H$13)*(1+'Summary Inputs & Assumptions'!$G42))) -> 6000 | J21: =IF(AND(J$6=YEAR('Summary Inputs & Assumptions'!$T$7),J$5<Debt!$C$3),'Summary Inputs & Assumptions'!#REF!*J$13,IF(J$5>'Summary Inputs & Assumptions'!$Q$41,0,(I21/I$13)*(1+'Summary Inputs & Assumptions'!$G42))) -> 6000 | K21: =IF(AND(K$6=YEAR('Summary Inputs & Assumptions'!$T$7),K$5<Debt!$C$3),'Summary Inputs & Assumptions'!#REF!*K$13,IF(K$5>'Summary Inputs & Assumptions'!$Q$41,0,(J21/J$13)*(1+'Summary Inputs & Assumptions'!$G42))) -> 6000 | L21: =IF(AND(L$6=YEAR('Summary Inputs & Assumptions'!$T$7),L$5<Debt!$C$3),'Summary Inputs & Assumptions'!#REF!*L$13,IF(L$5>'Summary Inputs & Assumptions'!$Q$41,0,(K21/K$13)*(1+'Summary Inputs & Assumptions'!$G42))) -> 6000 | M21: =IF(AND(M$6=YEAR('Summary Inputs & Assumptions'!$T$7),M$5<Debt!$C$3),'Summary Inputs & Assumptions'!#REF!*M$13,IF(M$5>'Summary Inputs & Assumptions'!$Q$41,0,(L21/L$13)*(1+'Summary Inputs & Assumptions'!$G42))) -> 6000 | N21: =IF(AND(N$6=YEAR('Summary Inputs & Assumptions'!$T$7),N$5<Debt!$C$3),'Summary Inputs & Assumptions'!#REF!*N$13,IF(N$5>'Summary Inputs & Assumptions'!$Q$41,0,(M21/M$13)*(1+'Summary Inputs & Assumptions'!$G42))) -> 6000 | O21: =IF(AND(O$6=YEAR('Summary Inputs & Assumptions'!$T$7),O$5<Debt!$C$3),'Summary Inputs & Assumptions'!#REF!*O$13,IF(O$5>'Summary Inputs & Assumptions'!$Q$41,0,(N21/N$13)*(1+'Summary Inputs & Assumptions'!$G42))) -> 6000 | ... AG21: =IF(AND(AG$6=YEAR('Summary Inputs & Assumptions'!$T$7),AG$5<Debt!$C$3),'Summary Inputs & Assumptions'!#REF!*AG$13,IF(AG$5>'Summary Inputs & Assumptions'!$Q$41,0,(AF21/AF$13)*(1+'Summary Inputs & Assumptions'!$G42))) -> 0
C22: ='Summary Inputs & Assumptions'!B43 -> Asset Management | D22: =IF(AND(D$6=YEAR('Summary Inputs & Assumptions'!$T$7),D$5<Debt!$C$3),'Summary Inputs & Assumptions'!$D$43*D$13,IF(D$5>Amortization_period,0,(C22*(1+'Summary Inputs & Assumptions'!$G43)))) -> 2739.726 | E22: =IF(AND(E$6=YEAR('Summary Inputs & Assumptions'!$T$7),E$5<Debt!$C$3),'Summary Inputs & Assumptions'!E43*E$13,IF(E$5>'Summary Inputs & Assumptions'!$Q$41,0,(D22/D$13)*(1+'Summary Inputs & Assumptions'!$G43))) -> 5000 | F22: =IF(AND(F$6=YEAR('Summary Inputs & Assumptions'!$T$7),F$5<Debt!$C$3),'Summary Inputs & Assumptions'!F43*F$13,IF(F$5>'Summary Inputs & Assumptions'!$Q$41,0,(E22/E$13)*(1+'Summary Inputs & Assumptions'!$G43))) -> 5000 | G22: =IF(AND(G$6=YEAR('Summary Inputs & Assumptions'!$T$7),G$5<Debt!$C$3),'Summary Inputs & Assumptions'!G43*G$13,IF(G$5>'Summary Inputs & Assumptions'!$Q$41,0,(F22/F$13)*(1+'Summary Inputs & Assumptions'!$G43))) -> 5000 | H22: =IF(AND(H$6=YEAR('Summary Inputs & Assumptions'!$T$7),H$5<Debt!$C$3),'Summary Inputs & Assumptions'!#REF!*H$13,IF(H$5>'Summary Inputs & Assumptions'!$Q$41,0,(G22/G$13)*(1+'Summary Inputs & Assumptions'!$G43))) -> 5000 | I22: =IF(AND(I$6=YEAR('Summary Inputs & Assumptions'!$T$7),I$5<Debt!$C$3),'Summary Inputs & Assumptions'!#REF!*I$13,IF(I$5>'Summary Inputs & Assumptions'!$Q$41,0,(H22/H$13)*(1+'Summary Inputs & Assumptions'!$G43))) -> 5000 | J22: =IF(AND(J$6=YEAR('Summary Inputs & Assumptions'!$T$7),J$5<Debt!$C$3),'Summary Inputs & Assumptions'!#REF!*J$13,IF(J$5>'Summary Inputs & Assumptions'!$Q$41,0,(I22/I$13)*(1+'Summary Inputs & Assumptions'!$G43))) -> 5000 | K22: =IF(AND(K$6=YEAR('Summary Inputs & Assumptions'!$T$7),K$5<Debt!$C$3),'Summary Inputs & Assumptions'!#REF!*K$13,IF(K$5>'Summary Inputs & Assumptions'!$Q$41,0,(J22/J$13)*(1+'Summary Inputs & Assumptions'!$G43))) -> 5000 | L22: =IF(AND(L$6=YEAR('Summary Inputs & Assumptions'!$T$7),L$5<Debt!$C$3),'Summary Inputs & Assumptions'!#REF!*L$13,IF(L$5>'Summary Inputs & Assumptions'!$Q$41,0,(K22/K$13)*(1+'Summary Inputs & Assumptions'!$G43))) -> 5000 | M22: =IF(AND(M$6=YEAR('Summary Inputs & Assumptions'!$T$7),M$5<Debt!$C$3),'Summary Inputs & Assumptions'!#REF!*M$13,IF(M$5>'Summary Inputs & Assumptions'!$Q$41,0,(L22/L$13)*(1+'Summary Inputs & Assumptions'!$G43))) -> 5000 | N22: =IF(AND(N$6=YEAR('Summary Inputs & Assumptions'!$T$7),N$5<Debt!$C$3),'Summary Inputs & Assumptions'!#REF!*N$13,IF(N$5>'Summary Inputs & Assumptions'!$Q$41,0,(M22/M$13)*(1+'Summary Inputs & Assumptions'!$G43))) -> 5000 | O22: =IF(AND(O$6=YEAR('Summary Inputs & Assumptions'!$T$7),O$5<Debt!$C$3),'Summary Inputs & Assumptions'!#REF!*O$13,IF(O$5>'Summary Inputs & Assumptions'!$Q$41,0,(N22/N$13)*(1+'Summary Inputs & Assumptions'!$G43))) -> 5000 | ... R22: =IF(AND(R$6=YEAR('Summary Inputs & Assumptions'!$T$7),R$5<Debt!$C$3),'Summary Inputs & Assumptions'!#REF!*R$13,IF(R$5>'Summary Inputs & Assumptions'!$Q$41,0,(Q22/Q$13)*(1+'Summary Inputs & Assumptions'!$G43))) -> 5000 | S22: =IF(AND(S$6=YEAR('Summary Inputs & Assumptions'!$T$7),S$5<Debt!$C$3),'Summary Inputs & Assumptions'!V63*S$13,IF(S$5>'Summary Inputs & Assumptions'!$Q$41,0,(R22/R$13)*(1+'Summary Inputs & Assumptions'!$G43))) -> 0 | T22: =IF(AND(T$6=YEAR('Summary Inputs & Assumptions'!$T$7),T$5<Debt!$C$3),'Summary Inputs & Assumptions'!W63*T$13,IF(T$5>'Summary Inputs & Assumptions'!$Q$41,0,(S22/S$13)*(1+'Summary Inputs & Assumptions'!$G43))) -> 0 | U22: =IF(AND(U$6=YEAR('Summary Inputs & Assumptions'!$T$7),U$5<Debt!$C$3),'Summary Inputs & Assumptions'!X63*U$13,IF(U$5>'Summary Inputs & Assumptions'!$Q$41,0,(T22/T$13)*(1+'Summary Inputs & Assumptions'!$G43))) -> 0 | V22: =IF(AND(V$6=YEAR('Summary Inputs & Assumptions'!$T$7),V$5<Debt!$C$3),'Summary Inputs & Assumptions'!Y63*V$13,IF(V$5>'Summary Inputs & Assumptions'!$Q$41,0,(U22/U$13)*(1+'Summary Inputs & Assumptions'!$G43))) -> 0 | W22: =IF(AND(W$6=YEAR('Summary Inputs & Assumptions'!$T$7),W$5<Debt!$C$3),'Summary Inputs & Assumptions'!Z63*W$13,IF(W$5>'Summary Inputs & Assumptions'!$Q$41,0,(V22/V$13)*(1+'Summary Inputs & Assumptions'!$G43))) -> 0 | X22: =IF(AND(X$6=YEAR('Summary Inputs & Assumptions'!$T$7),X$5<Debt!$C$3),'Summary Inputs & Assumptions'!AA61*X$13,IF(X$5>'Summary Inputs & Assumptions'!$Q$41,0,(W22/W$13)*(1+'Summary Inputs & Assumptions'!$G43))) -> 0 | Y22: =IF(AND(Y$6=YEAR('Summary Inputs & Assumptions'!$T$7),Y$5<Debt!$C$3),'Summary Inputs & Assumptions'!#REF!*Y$13,IF(Y$5>'Summary Inputs & Assumptions'!$Q$41,0,(X22/X$13)*(1+'Summary Inputs & Assumptions'!$G43))) -> 0 | Z22: =IF(AND(Z$6=YEAR('Summary Inputs & Assumptions'!$T$7),Z$5<Debt!$C$3),'Summary Inputs & Assumptions'!#REF!*Z$13,IF(Z$5>'Summary Inputs & Assumptions'!$Q$41,0,(Y22/Y$13)*(1+'Summary Inputs & Assumptions'!$G43))) -> 0 | AA22: =IF(AND(AA$6=YEAR('Summary Inputs & Assumptions'!$T$7),AA$5<Debt!$C$3),'Summary Inputs & Assumptions'!#REF!*AA$13,IF(AA$5>'Summary Inputs & Assumptions'!$Q$41,0,(Z22/Z$13)*(1+'Summary Inputs & Assumptions'!$G43))) -> 0 | AB22: =IF(AND(AB$6=YEAR('Summary Inputs & Assumptions'!$T$7),AB$5<Debt!$C$3),'Summary Inputs & Assumptions'!AB61*AB$13,IF(AB$5>'Summary Inputs & Assumptions'!$Q$41,0,(AA22/AA$13)*(1+'Summary Inputs & Assumptions'!$G43))) -> 0 | AC22: =IF(AND(AC$6=YEAR('Summary Inputs & Assumptions'!$T$7),AC$5<Debt!$C$3),'Summary Inputs & Assumptions'!AC61*AC$13,IF(AC$5>'Summary Inputs & Assumptions'!$Q$41,0,(AB22/AB$13)*(1+'Summary Inputs & Assumptions'!$G43))) -> 0 | AD22: =IF(AND(AD$6=YEAR('Summary Inputs & Assumptions'!$T$7),AD$5<Debt!$C$3),'Summary Inputs & Assumptions'!AD61*AD$13,IF(AD$5>'Summary Inputs & Assumptions'!$Q$41,0,(AC22/AC$13)*(1+'Summary Inputs & Assumptions'!$G43))) -> 0 | AE22: =IF(AND(AE$6=YEAR('Summary Inputs & Assumptions'!$T$7),AE$5<Debt!$C$3),'Summary Inputs & Assumptions'!AE61*AE$13,IF(AE$5>'Summary Inputs & Assumptions'!$Q$41,0,(AD22/AD$13)*(1+'Summary Inputs & Assumptions'!$G43))) -> 0 | AF22: =IF(AND(AF$6=YEAR('Summary Inputs & Assumptions'!$T$7),AF$5<Debt!$C$3),'Summary Inputs & Assumptions'!AF61*AF$13,IF(AF$5>'Summary Inputs & Assumptions'!$Q$41,0,(AE22/AE$13)*(1+'Summary Inputs & Assumptions'!$G43))) -> 0 | AG22: =IF(AND(AG$6=YEAR('Summary Inputs & Assumptions'!$T$7),AG$5<Debt!$C$3),'Summary Inputs & Assumptions'!AG61*AG$13,IF(AG$5>'Summary Inputs & Assumptions'!$Q$41,0,(AF22/AF$13)*(1+'Summary Inputs & Assumptions'!$G43))) -> 0
C23: ='Summary Inputs & Assumptions'!B44 -> Other | D23: =IF(AND(D$6=YEAR('Summary Inputs & Assumptions'!$T$7),D$5<Debt!$C$3),'Summary Inputs & Assumptions'!D44*D$13,IF(D$5>'Summary Inputs & Assumptions'!$Q$41,0,(C23*(1+'Summary Inputs & Assumptions'!$G44)))) -> 1643.8356 | E23: =IF(AND(E$6=YEAR('Summary Inputs & Assumptions'!$T$7),E$5<Debt!$C$3),'Summary Inputs & Assumptions'!E44*E$13,IF(E$5>'Summary Inputs & Assumptions'!$Q$41,0,(D23/D$13)*(1+'Summary Inputs & Assumptions'!$G44))) -> 3000 | F23: =IF(AND(F$6=YEAR('Summary Inputs & Assumptions'!$T$7),F$5<Debt!$C$3),'Summary Inputs & Assumptions'!F44*F$13,IF(F$5>'Summary Inputs & Assumptions'!$Q$41,0,(E23/E$13)*(1+'Summary Inputs & Assumptions'!$G44))) -> 3000 | G23: =IF(AND(G$6=YEAR('Summary Inputs & Assumptions'!$T$7),G$5<Debt!$C$3),'Summary Inputs & Assumptions'!G44*G$13,IF(G$5>'Summary Inputs & Assumptions'!$Q$41,0,(F23/F$13)*(1+'Summary Inputs & Assumptions'!$G44))) -> 3000 | H23: =IF(AND(H$6=YEAR('Summary Inputs & Assumptions'!$T$7),H$5<Debt!$C$3),'Summary Inputs & Assumptions'!#REF!*H$13,IF(H$5>'Summary Inputs & Assumptions'!$Q$41,0,(G23/G$13)*(1+'Summary Inputs & Assumptions'!$G44))) -> 3000 | I23: =IF(AND(I$6=YEAR('Summary Inputs & Assumptions'!$T$7),I$5<Debt!$C$3),'Summary Inputs & Assumptions'!#REF!*I$13,IF(I$5>'Summary Inputs & Assumptions'!$Q$41,0,(H23/H$13)*(1+'Summary Inputs & Assumptions'!$G44))) -> 3000 | J23: =IF(AND(J$6=YEAR('Summary Inputs & Assumptions'!$T$7),J$5<Debt!$C$3),'Summary Inputs & Assumptions'!#REF!*J$13,IF(J$5>'Summary Inputs & Assumptions'!$Q$41,0,(I23/I$13)*(1+'Summary Inputs & Assumptions'!$G44))) -> 3000 | K23: =IF(AND(K$6=YEAR('Summary Inputs & Assumptions'!$T$7),K$5<Debt!$C$3),'Summary Inputs & Assumptions'!#REF!*K$13,IF(K$5>'Summary Inputs & Assumptions'!$Q$41,0,(J23/J$13)*(1+'Summary Inputs & Assumptions'!$G44))) -> 3000 | L23: =IF(AND(L$6=YEAR('Summary Inputs & Assumptions'!$T$7),L$5<Debt!$C$3),'Summary Inputs & Assumptions'!#REF!*L$13,IF(L$5>'Summary Inputs & Assumptions'!$Q$41,0,(K23/K$13)*(1+'Summary Inputs & Assumptions'!$G44))) -> 3000 | M23: =IF(AND(M$6=YEAR('Summary Inputs & Assumptions'!$T$7),M$5<Debt!$C$3),'Summary Inputs & Assumptions'!#REF!*M$13,IF(M$5>'Summary Inputs & Assumptions'!$Q$41,0,(L23/L$13)*(1+'Summary Inputs & Assumptions'!$G44))) -> 3000 | N23: =IF(AND(N$6=YEAR('Summary Inputs & Assumptions'!$T$7),N$5<Debt!$C$3),'Summary Inputs & Assumptions'!#REF!*N$13,IF(N$5>'Summary Inputs & Assumptions'!$Q$41,0,(M23/M$13)*(1+'Summary Inputs & Assumptions'!$G44))) -> 3000 | O23: =IF(AND(O$6=YEAR('Summary Inputs & Assumptions'!$T$7),O$5<Debt!$C$3),'Summary Inputs & Assumptions'!#REF!*O$13,IF(O$5>'Summary Inputs & Assumptions'!$Q$41,0,(N23/N$13)*(1+'Summary Inputs & Assumptions'!$G44))) -> 3000 | ... R23: =IF(AND(R$6=YEAR('Summary Inputs & Assumptions'!$T$7),R$5<Debt!$C$3),'Summary Inputs & Assumptions'!#REF!*R$13,IF(R$5>'Summary Inputs & Assumptions'!$Q$41,0,(Q23/Q$13)*(1+'Summary Inputs & Assumptions'!$G44))) -> 3000 | S23: =IF(AND(S$6=YEAR('Summary Inputs & Assumptions'!$T$7),S$5<Debt!$C$3),'Summary Inputs & Assumptions'!V64*S$13,IF(S$5>'Summary Inputs & Assumptions'!$Q$41,0,(R23/R$13)*(1+'Summary Inputs & Assumptions'!$G44))) -> 0 | T23: =IF(AND(T$6=YEAR('Summary Inputs & Assumptions'!$T$7),T$5<Debt!$C$3),'Summary Inputs & Assumptions'!W64*T$13,IF(T$5>'Summary Inputs & Assumptions'!$Q$41,0,(S23/S$13)*(1+'Summary Inputs & Assumptions'!$G44))) -> 0 | U23: =IF(AND(U$6=YEAR('Summary Inputs & Assumptions'!$T$7),U$5<Debt!$C$3),'Summary Inputs & Assumptions'!X64*U$13,IF(U$5>'Summary Inputs & Assumptions'!$Q$41,0,(T23/T$13)*(1+'Summary Inputs & Assumptions'!$G44))) -> 0 | V23: =IF(AND(V$6=YEAR('Summary Inputs & Assumptions'!$T$7),V$5<Debt!$C$3),'Summary Inputs & Assumptions'!Y64*V$13,IF(V$5>'Summary Inputs & Assumptions'!$Q$41,0,(U23/U$13)*(1+'Summary Inputs & Assumptions'!$G44))) -> 0 | W23: =IF(AND(W$6=YEAR('Summary Inputs & Assumptions'!$T$7),W$5<Debt!$C$3),'Summary Inputs & Assumptions'!Z64*W$13,IF(W$5>'Summary Inputs & Assumptions'!$Q$41,0,(V23/V$13)*(1+'Summary Inputs & Assumptions'!$G44))) -> 0 | X23: =IF(AND(X$6=YEAR('Summary Inputs & Assumptions'!$T$7),X$5<Debt!$C$3),'Summary Inputs & Assumptions'!AA62*X$13,IF(X$5>'Summary Inputs & Assumptions'!$Q$41,0,(W23/W$13)*(1+'Summary Inputs & Assumptions'!$G44))) -> 0 | Y23: =IF(AND(Y$6=YEAR('Summary Inputs & Assumptions'!$T$7),Y$5<Debt!$C$3),'Summary Inputs & Assumptions'!#REF!*Y$13,IF(Y$5>'Summary Inputs & Assumptions'!$Q$41,0,(X23/X$13)*(1+'Summary Inputs & Assumptions'!$G44))) -> 0 | Z23: =IF(AND(Z$6=YEAR('Summary Inputs & Assumptions'!$T$7),Z$5<Debt!$C$3),'Summary Inputs & Assumptions'!#REF!*Z$13,IF(Z$5>'Summary Inputs & Assumptions'!$Q$41,0,(Y23/Y$13)*(1+'Summary Inputs & Assumptions'!$G44))) -> 0 | AA23: =IF(AND(AA$6=YEAR('Summary Inputs & Assumptions'!$T$7),AA$5<Debt!$C$3),'Summary Inputs & Assumptions'!#REF!*AA$13,IF(AA$5>'Summary Inputs & Assumptions'!$Q$41,0,(Z23/Z$13)*(1+'Summary Inputs & Assumptions'!$G44))) -> 0 | AB23: =IF(AND(AB$6=YEAR('Summary Inputs & Assumptions'!$T$7),AB$5<Debt!$C$3),'Summary Inputs & Assumptions'!AB62*AB$13,IF(AB$5>'Summary Inputs & Assumptions'!$Q$41,0,(AA23/AA$13)*(1+'Summary Inputs & Assumptions'!$G44))) -> 0 | AC23: =IF(AND(AC$6=YEAR('Summary Inputs & Assumptions'!$T$7),AC$5<Debt!$C$3),'Summary Inputs & Assumptions'!AC62*AC$13,IF(AC$5>'Summary Inputs & Assumptions'!$Q$41,0,(AB23/AB$13)*(1+'Summary Inputs & Assumptions'!$G44))) -> 0 | AD23: =IF(AND(AD$6=YEAR('Summary Inputs & Assumptions'!$T$7),AD$5<Debt!$C$3),'Summary Inputs & Assumptions'!AD62*AD$13,IF(AD$5>'Summary Inputs & Assumptions'!$Q$41,0,(AC23/AC$13)*(1+'Summary Inputs & Assumptions'!$G44))) -> 0 | AE23: =IF(AND(AE$6=YEAR('Summary Inputs & Assumptions'!$T$7),AE$5<Debt!$C$3),'Summary Inputs & Assumptions'!AE62*AE$13,IF(AE$5>'Summary Inputs & Assumptions'!$Q$41,0,(AD23/AD$13)*(1+'Summary Inputs & Assumptions'!$G44))) -> 0 | AF23: =IF(AND(AF$6=YEAR('Summary Inputs & Assumptions'!$T$7),AF$5<Debt!$C$3),'Summary Inputs & Assumptions'!AF62*AF$13,IF(AF$5>'Summary Inputs & Assumptions'!$Q$41,0,(AE23/AE$13)*(1+'Summary Inputs & Assumptions'!$G44))) -> 0 | AG23: =IF(AND(AG$6=YEAR('Summary Inputs & Assumptions'!$T$7),AG$5<Debt!$C$3),'Summary Inputs & Assumptions'!AG62*AG$13,IF(AG$5>'Summary Inputs & Assumptions'!$Q$41,0,(AF23/AF$13)*(1+'Summary Inputs & Assumptions'!$G44))) -> 0
C24: Depreciation Expense | D24: =IF('Summary Inputs & Assumptions'!$L$24="Yes",IF(AND(D$6=YEAR('Summary Inputs & Assumptions'!$T$9),'Summary Inputs & Assumptions'!$L$24="Yes"),'Summary Inputs & Assumptions'!$L$23,0),IFERROR(INDEX('Summary Inputs & Assumptions'!$J$27:$J$34,(MATCH((IF(YEAR('Summary Inputs & Assumptions'!$T$7)=D$6,1,C5+1)),'Summary Inputs & Assumptions'!$J$27:$J$34,0)),3),)*D$52) -> 0 | E24: =IF('Summary Inputs & Assumptions'!$L$24="Yes",IF(AND(E$6=YEAR('Summary Inputs & Assumptions'!$T$9),'Summary Inputs & Assumptions'!$L$24="Yes"),'Summary Inputs & Assumptions'!$L$23,0),IFERROR(INDEX('Summary Inputs & Assumptions'!$J$27:$J$34,(MATCH((IF(YEAR('Summary Inputs & Assumptions'!$T$7)=E$6,1,D5+1)),'Summary Inputs & Assumptions'!$J$27:$J$34,0)),3),)*E$52) -> 4964408 | F24: =IF('Summary Inputs & Assumptions'!$L$24="Yes",IF(AND(F$6=YEAR('Summary Inputs & Assumptions'!$T$9),'Summary Inputs & Assumptions'!$L$24="Yes"),'Summary Inputs & Assumptions'!$L$23,0),IFERROR(INDEX('Summary Inputs & Assumptions'!$J$27:$J$34,(MATCH((IF(YEAR('Summary Inputs & Assumptions'!$T$7)=F$6,1,E5+1)),'Summary Inputs & Assumptions'!$J$27:$J$34,0)),3),)*F$52) -> 0 | G24: =IF('Summary Inputs & Assumptions'!$L$24="Yes",IF(AND(G$6=YEAR('Summary Inputs & Assumptions'!$T$9),'Summary Inputs & Assumptions'!$L$24="Yes"),'Summary Inputs & Assumptions'!$L$23,0),IFERROR(INDEX('Summary Inputs & Assumptions'!$J$27:$J$34,(MATCH((IF(YEAR('Summary Inputs & Assumptions'!$T$7)=G$6,1,F5+1)),'Summary Inputs & Assumptions'!$J$27:$J$34,0)),3),)*G$52) -> 0 | H24: =IF('Summary Inputs & Assumptions'!$L$24="Yes",IF(AND(H$6=YEAR('Summary Inputs & Assumptions'!$T$9),'Summary Inputs & Assumptions'!$L$24="Yes"),'Summary Inputs & Assumptions'!$L$23,0),IFERROR(INDEX('Summary Inputs & Assumptions'!$J$27:$J$34,(MATCH((IF(YEAR('Summary Inputs & Assumptions'!$T$7)=H$6,1,G5+1)),'Summary Inputs & Assumptions'!$J$27:$J$34,0)),3),)*H$52) -> 0 | I24: =IF('Summary Inputs & Assumptions'!$L$24="Yes",IF(AND(I$6=YEAR('Summary Inputs & Assumptions'!$T$9),'Summary Inputs & Assumptions'!$L$24="Yes"),'Summary Inputs & Assumptions'!$L$23,0),IFERROR(INDEX('Summary Inputs & Assumptions'!$J$27:$J$34,(MATCH((IF(YEAR('Summary Inputs & Assumptions'!$T$7)=I$6,1,H5+1)),'Summary Inputs & Assumptions'!$J$27:$J$34,0)),3),)*I$52) -> 0 | J24: =IF('Summary Inputs & Assumptions'!$L$24="Yes",IF(AND(J$6=YEAR('Summary Inputs & Assumptions'!$T$9),'Summary Inputs & Assumptions'!$L$24="Yes"),'Summary Inputs & Assumptions'!$L$23,0),IFERROR(INDEX('Summary Inputs & Assumptions'!$J$27:$J$34,(MATCH((IF(YEAR('Summary Inputs & Assumptions'!$T$7)=J$6,1,I5+1)),'Summary Inputs & Assumptions'!$J$27:$J$34,0)),3),)*J$52) -> 0 | K24: =IF('Summary Inputs & Assumptions'!$L$24="Yes",IF(AND(K$6=YEAR('Summary Inputs & Assumptions'!$T$9),'Summary Inputs & Assumptions'!$L$24="Yes"),'Summary Inputs & Assumptions'!$L$23,0),IFERROR(INDEX('Summary Inputs & Assumptions'!$J$27:$J$34,(MATCH((IF(YEAR('Summary Inputs & Assumptions'!$T$7)=K$6,1,J5+1)),'Summary Inputs & Assumptions'!$J$27:$J$34,0)),3),)*K$52) -> 0 | ... AG24: =IF('Summary Inputs & Assumptions'!$L$24="Yes",IF(AND(AG$6=YEAR('Summary Inputs & Assumptions'!$T$9),'Summary Inputs & Assumptions'!$L$24="Yes"),'Summary Inputs & Assumptions'!$L$23,0),IFERROR(INDEX('Summary Inputs & Assumptions'!$J$27:$J$34,(MATCH((IF(YEAR('Summary Inputs & Assumptions'!$T$7)=AG$6,1,AF5+1)),'Summary Inputs & Assumptions'!$J$27:$J$34,0)),3),)*AG$52) -> 0
C26: NOI | D26: =D15-SUM(D18:D24) -> 136859.18 | E26: =E15-SUM(E18:E24) -> -4715831.9 | F26: =F15-SUM(F18:F24) -> 247379.95 | G26: =G15-SUM(G18:G24) -> 246179.41 | H26: =H15-SUM(H18:H24) -> 244974.34 | I26: =I15-SUM(I18:I24) -> 243764.59 | J26: =J15-SUM(J18:J24) -> 242550 | K26: =K15-SUM(K18:K24) -> 241330.42 | ... AG26: =AG15-SUM(AG18:AG24) -> 0
C28: Total Interest Expense | D28: =IFERROR(-INDEX(Debt!$B$7:$K$45,MATCH(D$6,Debt!$B$7:$B$44,0),(MATCH(TRIM($C28),Debt!$B$7:$K$7,0))),0) -> -80278.2 | E28: =IFERROR(-INDEX(Debt!$B$7:$K$45,MATCH(E$6,Debt!$B$7:$B$44,0),(MATCH(TRIM($C28),Debt!$B$7:$K$7,0))),0) -> -79730.137 | F28: =IFERROR(-INDEX(Debt!$B$7:$K$45,MATCH(F$6,Debt!$B$7:$B$44,0),(MATCH(TRIM($C28),Debt!$B$7:$K$7,0))),0) -> -75430.774 | G28: =IFERROR(-INDEX(Debt!$B$7:$K$45,MATCH(G$6,Debt!$B$7:$B$44,0),(MATCH(TRIM($C28),Debt!$B$7:$K$7,0))),0) -> -70956.315 | H28: =IFERROR(-INDEX(Debt!$B$7:$K$45,MATCH(H$6,Debt!$B$7:$B$44,0),(MATCH(TRIM($C28),Debt!$B$7:$K$7,0))),0) -> -66298.15 | I28: =IFERROR(-INDEX(Debt!$B$7:$K$45,MATCH(I$6,Debt!$B$7:$B$44,0),(MATCH(TRIM($C28),Debt!$B$7:$K$7,0))),0) -> -61447.246 | J28: =IFERROR(-INDEX(Debt!$B$7:$K$45,MATCH(J$6,Debt!$B$7:$B$44,0),(MATCH(TRIM($C28),Debt!$B$7:$K$7,0))),0) -> -56394.122 | K28: =IFERROR(-INDEX(Debt!$B$7:$K$45,MATCH(K$6,Debt!$B$7:$B$44,0),(MATCH(TRIM($C28),Debt!$B$7:$K$7,0))),0) -> -51128.829 | ... AG28: =IFERROR(-INDEX(Debt!$B$7:$K$45,MATCH(AG$6,Debt!$B$7:$B$44,0),(MATCH(TRIM($C28),Debt!$B$7:$K$7,0))),0) -> 0
C30: Taxable Income / (Loss) | D30: =D26-D28 -> 217137.38 | E30: =E26-E28 -> -4636101.8 | F30: =F26-F28 -> 322810.72 | G30: =G26-G28 -> 317135.73 | H30: =H26-H28 -> 311272.49 | I30: =I26-I28 -> 305211.83 | J30: =J26-J28 -> 298944.12 | K30: =K26-K28 -> 292459.25 | ... AG30: =AG26-AG28 -> 0
C32: ="EBITDA "&B2 -> EBITDA P50 | D32: =OFFSET(D35,(IF(B2="P50",0,2)),0) -> 136859.18 | E32: =OFFSET(E35,(IF(C2="P50",0,2)),0) -> 208939.84 | F32: =OFFSET(F35,(IF(D2="P50",0,2)),0) -> 207862.6 | G32: =OFFSET(G35,(IF(E2="P50",0,2)),0) -> 206780.62 | H32: =OFFSET(H35,(IF(F2="P50",0,2)),0) -> 205693.74 | I32: =OFFSET(I35,(IF(G2="P50",0,2)),0) -> 204601.83 | J32: =OFFSET(J35,(IF(H2="P50",0,2)),0) -> 203504.73 | K32: =OFFSET(K35,(IF(I2="P50",0,2)),0) -> 202402.29 | ... AG32: =OFFSET(AG35,(IF(AE2="P50",0,2)),0) -> 0
C35: EBITDA P50 | D35: =D26+D24 -> 136859.18 | E35: =E26+E24 -> 248576.1 | F35: =F26+F24 -> 247379.95 | G35: =G26+G24 -> 246179.41 | H35: =H26+H24 -> 244974.34 | I35: =I26+I24 -> 243764.59 | J35: =J26+J24 -> 242550 | K35: =K26+K24 -> 241330.42 | ... AG35: =AG26+AG24 -> 0
C37: EBITDA P99 | D37: =(((D15*'Summary Inputs & Assumptions'!$F$25)-SUM(D18:D24)))+D24 -> 115075.33 | E37: =(((E15*'Summary Inputs & Assumptions'!$F$25)-SUM(E18:E24)))+E24 -> 208939.84 | F37: =(((F15*'Summary Inputs & Assumptions'!$F$25)-SUM(F18:F24)))+F24 -> 207862.6 | G37: =(((G15*'Summary Inputs & Assumptions'!$F$25)-SUM(G18:G24)))+G24 -> 206780.62 | H37: =(((H15*'Summary Inputs & Assumptions'!$F$25)-SUM(H18:H24)))+H24 -> 205693.74 | I37: =(((I15*'Summary Inputs & Assumptions'!$F$25)-SUM(I18:I24)))+I24 -> 204601.83 | J37: =(((J15*'Summary Inputs & Assumptions'!$F$25)-SUM(J18:J24)))+J24 -> 203504.73 | K37: =(((K15*'Summary Inputs & Assumptions'!$F$25)-SUM(K18:K24)))+K24 -> 202402.29 | ... AG37: =(((AG15*'Summary Inputs & Assumptions'!$F$25)-SUM(AG18:AG24)))+AG24 -> 0
B43: Balance Sheet
C45: =C6 -> Year | D45: =D6 -> 2022 | E45: =E6 -> 2023 | F45: =F6 -> 2024 | G45: =G6 -> 2025 | H45: =H6 -> 2026 | I45: =I6 -> 2027 | J45: =J6 -> 2028 | ... AG45: =AG6 -> 0
B47: Current Assets
C48: Cash | D48: =_xlfn.IFNA(D98,0) -> 4592703.5 | E48: =_xlfn.IFNA(E98,0) -> 1309274.4 | F48: =_xlfn.IFNA(F98,0) -> 1546097.8 | G48: =_xlfn.IFNA(G98,0) -> 1773744.4 | H48: =_xlfn.IFNA(H98,0) -> 1991853.6 | I48: =_xlfn.IFNA(I98,0) -> 2200047.3 | J48: =_xlfn.IFNA(J98,0) -> 2397929 | K48: =_xlfn.IFNA(K98,0) -> 2585082.3 | ... AG48: =_xlfn.IFNA(AG98,0) -> 0
C49: Receivables | D49: 0 | E49: 0 | F49: 0 | G49: 0 | H49: 0 | I49: 0 | J49: 0 | K49: 0 | L49: 0 | M49: 0 | N49: 0 | O49: 0 | P49: 0 | Q49: 0 | R49: 0 | S49: 0 | T49: 0 | U49: 0 | V49: 0 | W49: 0 | X49: 0 | Y49: 0 | Z49: 0 | AA49: 0 | AB49: 0 | AC49: 0 | AD49: 0 | AE49: 0 | AF49: 0 | AG49: 0
B51: Fixed Assets
C52: Depreciable Basis | D52: =IF(D$6>=YEAR('Summary Inputs & Assumptions'!$T$9),'Summary Inputs & Assumptions'!$L$23,0) -> 0 | E52: =IF(E$6>=YEAR('Summary Inputs & Assumptions'!$T$9),'Summary Inputs & Assumptions'!$L$23,0) -> 4964408 | F52: =IF(F$6>=YEAR('Summary Inputs & Assumptions'!$T$9),'Summary Inputs & Assumptions'!$L$23,0) -> 4964408 | G52: =IF(G$6>=YEAR('Summary Inputs & Assumptions'!$T$9),'Summary Inputs & Assumptions'!$L$23,0) -> 4964408 | H52: =IF(H$6>=YEAR('Summary Inputs & Assumptions'!$T$9),'Summary Inputs & Assumptions'!$L$23,0) -> 4964408 | I52: =IF(I$6>=YEAR('Summary Inputs & Assumptions'!$T$9),'Summary Inputs & Assumptions'!$L$23,0) -> 4964408 | J52: =IF(J$6>=YEAR('Summary Inputs & Assumptions'!$T$9),'Summary Inputs & Assumptions'!$L$23,0) -> 4964408 | K52: =IF(K$6>=YEAR('Summary Inputs & Assumptions'!$T$9),'Summary Inputs & Assumptions'!$L$23,0) -> 4964408 | ... AG52: =IF(AG$6>=YEAR('Summary Inputs & Assumptions'!$T$9),'Summary Inputs & Assumptions'!$L$23,0) -> 0
C53: Accumulated Depreciation | D53: =-D24 -> 0 | E53: =IF(E45=0,0,D53-E24) -> -4964408 | F53: =IF(F45=0,0,E53-F24) -> -4964408 | G53: =IF(G45=0,0,F53-G24) -> -4964408 | H53: =IF(H45=0,0,G53-H24) -> -4964408 | I53: =IF(I45=0,0,H53-I24) -> -4964408 | J53: =IF(J45=0,0,I53-J24) -> -4964408 | K53: =IF(K45=0,0,J53-K24) -> -4964408 | L53: =IF(L45=0,0,K53-L24) -> -4964408 | ... AG53: =IF(AG45=0,0,AF53-AG24) -> 0
C54: Net Fixed Assets | D54: =SUM(D53,D52) -> 0 | E54: =SUM(E53,E52) -> 0 | F54: =SUM(F53,F52) -> 0 | G54: =SUM(G53,G52) -> 0 | H54: =SUM(H53,H52) -> 0 | I54: =SUM(I53,I52) -> 0 | J54: =SUM(J53,J52) -> 0 | K54: =SUM(K53,K52) -> 0 | ... AG54: =SUM(AG53,AG52) -> 0
B56: Total Assets | D56: =D54+D49+D48 -> 4592703.5 | E56: =E54+E49+E48 -> 1309274.4 | F56: =F54+F49+F48 -> 1546097.8 | G56: =G54+G49+G48 -> 1773744.4 | H56: =H54+H49+H48 -> 1991853.6 | I56: =I54+I49+I48 -> 2200047.3 | J56: =J54+J49+J48 -> 2397929 | K56: =K54+K49+K48 -> 2585082.3 | ... AG56: =AG54+AG49+AG48 -> 0
B58: Liability
C60: Debt
C61: End Balance | D61: =_xlfn.IFNA(INDEX(Debt!$A$7:$K$45,MATCH(D$6,Debt!$B$7:$B$44,0),(MATCH($C61,Debt!$B$7:$K$7,0))),0) -> 1605564 | E61: =_xlfn.IFNA(INDEX(Debt!$A$7:$K$45,MATCH(E$6,Debt!$B$7:$B$44,0),(MATCH($C61,Debt!$B$7:$K$7,0))),0) -> 1594602.7 | F61: =_xlfn.IFNA(INDEX(Debt!$A$7:$K$45,MATCH(F$6,Debt!$B$7:$B$44,0),(MATCH($C61,Debt!$B$7:$K$7,0))),0) -> 1508615.5 | G61: =_xlfn.IFNA(INDEX(Debt!$A$7:$K$45,MATCH(G$6,Debt!$B$7:$B$44,0),(MATCH($C61,Debt!$B$7:$K$7,0))),0) -> 1419126.3 | H61: =_xlfn.IFNA(INDEX(Debt!$A$7:$K$45,MATCH(H$6,Debt!$B$7:$B$44,0),(MATCH($C61,Debt!$B$7:$K$7,0))),0) -> 1325963 | I61: =_xlfn.IFNA(INDEX(Debt!$A$7:$K$45,MATCH(I$6,Debt!$B$7:$B$44,0),(MATCH($C61,Debt!$B$7:$K$7,0))),0) -> 1228944.9 | J61: =_xlfn.IFNA(INDEX(Debt!$A$7:$K$45,MATCH(J$6,Debt!$B$7:$B$44,0),(MATCH($C61,Debt!$B$7:$K$7,0))),0) -> 1127882.4 | K61: =_xlfn.IFNA(INDEX(Debt!$A$7:$K$45,MATCH(K$6,Debt!$B$7:$B$44,0),(MATCH($C61,Debt!$B$7:$K$7,0))),0) -> 1022576.6 | ... AG61: =_xlfn.IFNA(INDEX(Debt!$A$7:$K$45,MATCH(AG$6,Debt!$B$7:$B$44,0),(MATCH($C61,Debt!$B$7:$K$7,0))),0) -> 0
C62: Total Liabilitues | D62: =SUM(D59:D61) -> 1605564 | E62: =SUM(E59:E61) -> 1594602.7 | F62: =SUM(F59:F61) -> 1508615.5 | G62: =SUM(G59:G61) -> 1419126.3 | H62: =SUM(H59:H61) -> 1325963 | I62: =SUM(I59:I61) -> 1228944.9 | J62: =SUM(J59:J61) -> 1127882.4 | K62: =SUM(K59:K61) -> 1022576.6 | ... AG62: =SUM(AG59:AG61) -> 0
C64: Owners Equity
C65: Retained Earnings | D65: =D30 -> 217137.38 | E65: =IF(E45=0,0,E30+D65) -> -4418964.4 | F65: =IF(F45=0,0,F30+E65) -> -4096153.7 | G65: =IF(G45=0,0,G30+F65) -> -3779017.9 | H65: =IF(H45=0,0,H30+G65) -> -3467745.4 | I65: =IF(I45=0,0,I30+H65) -> -3162533.6 | J65: =IF(J45=0,0,J30+I65) -> -2863589.5 | K65: =IF(K45=0,0,K30+J65) -> -2571130.2 | L65: =IF(L45=0,0,L30+K65) -> -2285383.6 | ... AG65: =IF(AG45=0,0,AG30+AF65) -> 0
C66: Cash Distributions
C67: Paid In Capital (Tax Equity) | D67: =IF(D45=0,0,IF(_xlfn.IFNA(INDEX('Capital Contribution Schedule'!$B$13:$E$36,MATCH(D$45,'Capital Contribution Schedule'!$B$13:$B$22,0),MATCH($C67,'Capital Contribution Schedule'!$B$13:$E$13,0)),0)=0,$B67,$B67+_xlfn.IFNA(INDEX('Capital Contribution Schedule'!$B$13:$E$36,MATCH(D$45,'Capital Contribution Schedule'!$B$13:$B$22,0),MATCH($C67,'Capital Contribution Schedule'!$B$13:$E$13,0)),0))) -> 340908.48 | E67: =IF(E45=0,0,IF(_xlfn.IFNA(INDEX('Capital Contribution Schedule'!$B$13:$E$36,MATCH(E$45,'Capital Contribution Schedule'!$B$13:$B$22,0),MATCH($C67,'Capital Contribution Schedule'!$B$13:$E$13,0)),0)=0,D67,D67+_xlfn.IFNA(INDEX('Capital Contribution Schedule'!$B$13:$E$36,MATCH(E$45,'Capital Contribution Schedule'!$B$13:$B$22,0),MATCH($C67,'Capital Contribution Schedule'!$B$13:$E$13,0)),0))) -> 1704542.4 | F67: =IF(F45=0,0,IF(_xlfn.IFNA(INDEX('Capital Contribution Schedule'!$B$13:$E$36,MATCH(F$45,'Capital Contribution Schedule'!$B$13:$B$22,0),MATCH($C67,'Capital Contribution Schedule'!$B$13:$E$13,0)),0)=0,E67,E67+_xlfn.IFNA(INDEX('Capital Contribution Schedule'!$B$13:$E$36,MATCH(F$45,'Capital Contribution Schedule'!$B$13:$B$22,0),MATCH($C67,'Capital Contribution Schedule'!$B$13:$E$13,0)),0))) -> 1704542.4 | G67: =IF(G45=0,0,IF(_xlfn.IFNA(INDEX('Capital Contribution Schedule'!$B$13:$E$36,MATCH(G$45,'Capital Contribution Schedule'!$B$13:$B$22,0),MATCH($C67,'Capital Contribution Schedule'!$B$13:$E$13,0)),0)=0,F67,F67+_xlfn.IFNA(INDEX('Capital Contribution Schedule'!$B$13:$E$36,MATCH(G$45,'Capital Contribution Schedule'!$B$13:$B$22,0),MATCH($C67,'Capital Contribution Schedule'!$B$13:$E$13,0)),0))) -> 1704542.4 | H67: =IF(H45=0,0,IF(_xlfn.IFNA(INDEX('Capital Contribution Schedule'!$B$13:$E$36,MATCH(H$45,'Capital Contribution Schedule'!$B$13:$B$22,0),MATCH($C67,'Capital Contribution Schedule'!$B$13:$E$13,0)),0)=0,G67,G67+_xlfn.IFNA(INDEX('Capital Contribution Schedule'!$B$13:$E$36,MATCH(H$45,'Capital Contribution Schedule'!$B$13:$B$22,0),MATCH($C67,'Capital Contribution Schedule'!$B$13:$E$13,0)),0))) -> 1704542.4 | I67: =IF(I45=0,0,IF(_xlfn.IFNA(INDEX('Capital Contribution Schedule'!$B$13:$E$36,MATCH(I$45,'Capital Contribution Schedule'!$B$13:$B$22,0),MATCH($C67,'Capital Contribution Schedule'!$B$13:$E$13,0)),0)=0,H67,H67+_xlfn.IFNA(INDEX('Capital Contribution Schedule'!$B$13:$E$36,MATCH(I$45,'Capital Contribution Schedule'!$B$13:$B$22,0),MATCH($C67,'Capital Contribution Schedule'!$B$13:$E$13,0)),0))) -> 1704542.4 | J67: =IF(J45=0,0,IF(_xlfn.IFNA(INDEX('Capital Contribution Schedule'!$B$13:$E$36,MATCH(J$45,'Capital Contribution Schedule'!$B$13:$B$22,0),MATCH($C67,'Capital Contribution Schedule'!$B$13:$E$13,0)),0)=0,I67,I67+_xlfn.IFNA(INDEX('Capital Contribution Schedule'!$B$13:$E$36,MATCH(J$45,'Capital Contribution Schedule'!$B$13:$B$22,0),MATCH($C67,'Capital Contribution Schedule'!$B$13:$E$13,0)),0))) -> 1704542.4 | K67: =IF(K45=0,0,IF(_xlfn.IFNA(INDEX('Capital Contribution Schedule'!$B$13:$E$36,MATCH(K$45,'Capital Contribution Schedule'!$B$13:$B$22,0),MATCH($C67,'Capital Contribution Schedule'!$B$13:$E$13,0)),0)=0,J67,J67+_xlfn.IFNA(INDEX('Capital Contribution Schedule'!$B$13:$E$36,MATCH(K$45,'Capital Contribution Schedule'!$B$13:$B$22,0),MATCH($C67,'Capital Contribution Schedule'!$B$13:$E$13,0)),0))) -> 1704542.4 | L67: =IF(L45=0,0,IF(_xlfn.IFNA(INDEX('Capital Contribution Schedule'!$B$13:$E$36,MATCH(L$45,'Capital Contribution Schedule'!$B$13:$B$22,0),MATCH($C67,'Capital Contribution Schedule'!$B$13:$E$13,0)),0)=0,K67,K67+_xlfn.IFNA(INDEX('Capital Contribution Schedule'!$B$13:$E$36,MATCH(L$45,'Capital Contribution Schedule'!$B$13:$B$22,0),MATCH($C67,'Capital Contribution Schedule'!$B$13:$E$13,0)),0))) -> 1704542.4 | ... AG67: =IF(AG45=0,0,IF(_xlfn.IFNA(INDEX('Capital Contribution Schedule'!$B$13:$E$36,MATCH(AG$45,'Capital Contribution Schedule'!$B$13:$B$22,0),MATCH($C67,'Capital Contribution Schedule'!$B$13:$E$13,0)),0)=0,AF67,AF67+_xlfn.IFNA(INDEX('Capital Contribution Schedule'!$B$13:$E$36,MATCH(AG$45,'Capital Contribution Schedule'!$B$13:$B$22,0),MATCH($C67,'Capital Contribution Schedule'!$B$13:$E$13,0)),0))) -> 0
C68: Paid in Capital GP | D68: =IF(_xlfn.IFNA(INDEX('Capital Contribution Schedule'!$B$13:$E$36,MATCH(D$45,'Capital Contribution Schedule'!$B$13:$B$22,0),MATCH($C68,'Capital Contribution Schedule'!$B$13:$E$13,0)),0)=0,$B68,$B68+_xlfn.IFNA(INDEX('Capital Contribution Schedule'!$B$13:$E$36,MATCH(D$45,'Capital Contribution Schedule'!$B$13:$B$22,0),MATCH($C68,'Capital Contribution Schedule'!$B$13:$E$13,0)),0)) -> 2429093.6 | E68: =IF(E45=0,0,IF(_xlfn.IFNA(INDEX('Capital Contribution Schedule'!$B$13:$E$36,MATCH(E$45,'Capital Contribution Schedule'!$B$13:$B$22,0),MATCH($C68,'Capital Contribution Schedule'!$B$13:$E$13,0)),0)=0,D68,D68+_xlfn.IFNA(INDEX('Capital Contribution Schedule'!$B$13:$E$36,MATCH(E$45,'Capital Contribution Schedule'!$B$13:$B$22,0),MATCH($C68,'Capital Contribution Schedule'!$B$13:$E$13,0)),0))) -> 2429093.6 | F68: =IF(F45=0,0,IF(_xlfn.IFNA(INDEX('Capital Contribution Schedule'!$B$13:$E$36,MATCH(F$45,'Capital Contribution Schedule'!$B$13:$B$22,0),MATCH($C68,'Capital Contribution Schedule'!$B$13:$E$13,0)),0)=0,E68,E68+_xlfn.IFNA(INDEX('Capital Contribution Schedule'!$B$13:$E$36,MATCH(F$45,'Capital Contribution Schedule'!$B$13:$B$22,0),MATCH($C68,'Capital Contribution Schedule'!$B$13:$E$13,0)),0))) -> 2429093.6 | G68: =IF(G45=0,0,IF(_xlfn.IFNA(INDEX('Capital Contribution Schedule'!$B$13:$E$36,MATCH(G$45,'Capital Contribution Schedule'!$B$13:$B$22,0),MATCH($C68,'Capital Contribution Schedule'!$B$13:$E$13,0)),0)=0,F68,F68+_xlfn.IFNA(INDEX('Capital Contribution Schedule'!$B$13:$E$36,MATCH(G$45,'Capital Contribution Schedule'!$B$13:$B$22,0),MATCH($C68,'Capital Contribution Schedule'!$B$13:$E$13,0)),0))) -> 2429093.6 | H68: =IF(H45=0,0,IF(_xlfn.IFNA(INDEX('Capital Contribution Schedule'!$B$13:$E$36,MATCH(H$45,'Capital Contribution Schedule'!$B$13:$B$22,0),MATCH($C68,'Capital Contribution Schedule'!$B$13:$E$13,0)),0)=0,G68,G68+_xlfn.IFNA(INDEX('Capital Contribution Schedule'!$B$13:$E$36,MATCH(H$45,'Capital Contribution Schedule'!$B$13:$B$22,0),MATCH($C68,'Capital Contribution Schedule'!$B$13:$E$13,0)),0))) -> 2429093.6 | I68: =IF(I45=0,0,IF(_xlfn.IFNA(INDEX('Capital Contribution Schedule'!$B$13:$E$36,MATCH(I$45,'Capital Contribution Schedule'!$B$13:$B$22,0),MATCH($C68,'Capital Contribution Schedule'!$B$13:$E$13,0)),0)=0,H68,H68+_xlfn.IFNA(INDEX('Capital Contribution Schedule'!$B$13:$E$36,MATCH(I$45,'Capital Contribution Schedule'!$B$13:$B$22,0),MATCH($C68,'Capital Contribution Schedule'!$B$13:$E$13,0)),0))) -> 2429093.6 | J68: =IF(J45=0,0,IF(_xlfn.IFNA(INDEX('Capital Contribution Schedule'!$B$13:$E$36,MATCH(J$45,'Capital Contribution Schedule'!$B$13:$B$22,0),MATCH($C68,'Capital Contribution Schedule'!$B$13:$E$13,0)),0)=0,I68,I68+_xlfn.IFNA(INDEX('Capital Contribution Schedule'!$B$13:$E$36,MATCH(J$45,'Capital Contribution Schedule'!$B$13:$B$22,0),MATCH($C68,'Capital Contribution Schedule'!$B$13:$E$13,0)),0))) -> 2429093.6 | K68: =IF(K45=0,0,IF(_xlfn.IFNA(INDEX('Capital Contribution Schedule'!$B$13:$E$36,MATCH(K$45,'Capital Contribution Schedule'!$B$13:$B$22,0),MATCH($C68,'Capital Contribution Schedule'!$B$13:$E$13,0)),0)=0,J68,J68+_xlfn.IFNA(INDEX('Capital Contribution Schedule'!$B$13:$E$36,MATCH(K$45,'Capital Contribution Schedule'!$B$13:$B$22,0),MATCH($C68,'Capital Contribution Schedule'!$B$13:$E$13,0)),0))) -> 2429093.6 | L68: =IF(L45=0,0,IF(_xlfn.IFNA(INDEX('Capital Contribution Schedule'!$B$13:$E$36,MATCH(L$45,'Capital Contribution Schedule'!$B$13:$B$22,0),MATCH($C68,'Capital Contribution Schedule'!$B$13:$E$13,0)),0)=0,K68,K68+_xlfn.IFNA(INDEX('Capital Contribution Schedule'!$B$13:$E$36,MATCH(L$45,'Capital Contribution Schedule'!$B$13:$B$22,0),MATCH($C68,'Capital Contribution Schedule'!$B$13:$E$13,0)),0))) -> 2429093.6 | ... AG68: =IF(AG45=0,0,IF(_xlfn.IFNA(INDEX('Capital Contribution Schedule'!$B$13:$E$36,MATCH(AG$45,'Capital Contribution Schedule'!$B$13:$B$22,0),MATCH($C68,'Capital Contribution Schedule'!$B$13:$E$13,0)),0)=0,AF68,AF68+_xlfn.IFNA(INDEX('Capital Contribution Schedule'!$B$13:$E$36,MATCH(AG$45,'Capital Contribution Schedule'!$B$13:$B$22,0),MATCH($C68,'Capital Contribution Schedule'!$B$13:$E$13,0)),0))) -> 0
C69: Total Owners Equity | D69: =SUM(D65:D68) -> 2987139.5 | E69: =SUM(E65:E68) -> -285328.39 | F69: =SUM(F65:F68) -> 37482.334 | G69: =SUM(G65:G68) -> 354618.06 | H69: =SUM(H65:H68) -> 665890.55 | I69: =SUM(I65:I68) -> 971102.38 | J69: =SUM(J65:J68) -> 1270046.5 | K69: =SUM(K65:K68) -> 1562505.8 | ... AG69: =SUM(AG65:AG68) -> 0
C71: Total Liabilities and OE | D71: =D69+D62 -> 4592703.5 | E71: =E69+E62 -> 1309274.4 | F71: =F69+F62 -> 1546097.8 | G71: =G69+G62 -> 1773744.4 | H71: =H69+H62 -> 1991853.6 | I71: =I69+I62 -> 2200047.3 | J71: =J69+J62 -> 2397929 | K71: =K69+K62 -> 2585082.3 | ... AG71: =AG69+AG62 -> 0
D73: =D56-D71 -> 0 | E73: =E56-E71 -> 0 | F73: =F56-F71 -> 0 | G73: =G56-G71 -> 0 | H73: =H56-H71 -> 0 | I73: =I56-I71 -> 0 | J73: =J56-J71 -> 0 | K73: =K56-K71 -> 0 | ... AG73: =AG56-AG71 -> 0
B78: Cashflow Statement
C80: =C45 -> Year | D80: =D45 -> 2022 | E80: =E45 -> 2023 | F80: =F45 -> 2024 | G80: =G45 -> 2025 | H80: =H45 -> 2026 | I80: =I45 -> 2027 | J80: =J45 -> 2028 | ... AG80: =AG45 -> 0
C82: Taxable Income | D82: =D30 -> 217137.38 | E82: =E30 -> -4636101.8 | F82: =F30 -> 322810.72 | G82: =G30 -> 317135.73 | H82: =H30 -> 311272.49 | I82: =I30 -> 305211.83 | J82: =J30 -> 298944.12 | K82: =K30 -> 292459.25 | ... AG82: =AG30 -> 0
C83: Depreciation | D83: =D24 -> 0 | E83: =E24 -> 4964408 | F83: =F24 -> 0 | G83: =G24 -> 0 | H83: =H24 -> 0 | I83: =I24 -> 0 | J83: =J24 -> 0 | K83: =K24 -> 0 | ... AG83: =AG24 -> 0
E84: =E24 -> 4964408 | F84: =F24 -> 0 | G84: =G24 -> 0 | H84: =H24 -> 0 | I84: =I24 -> 0 | J84: =J24 -> 0 | K84: =K24 -> 0 | L84: =L24 -> 0 | ... AG84: =AG24 -> 0
C85: Total Cashflow from Operations | D85: =SUM(D82:D83) -> 217137.38 | E85: =SUM(E82:E83) -> 328306.23 | F85: =SUM(F82:F83) -> 322810.72 | G85: =SUM(G82:G83) -> 317135.73 | H85: =SUM(H82:H83) -> 311272.49 | I85: =SUM(I82:I83) -> 305211.83 | J85: =SUM(J82:J83) -> 298944.12 | K85: =SUM(K82:K83) -> 292459.25 | ... AG85: =SUM(AG82:AG83) -> 0
C88: Total Cashflow from Investing | D88: =IF(D80=YEAR('Summary Inputs & Assumptions'!$T$7),-D52,IF(D80=0,0,-(D52-C52))) -> 0 | E88: =IF(E80=YEAR('Summary Inputs & Assumptions'!$T$7),-E52,IF(E80=0,0,-(E52-D52))) -> -4964408 | F88: =IF(F80=YEAR('Summary Inputs & Assumptions'!$T$7),-F52,IF(F80=0,0,-(F52-E52))) -> 0 | G88: =IF(G80=YEAR('Summary Inputs & Assumptions'!$T$7),-G52,IF(G80=0,0,-(G52-F52))) -> 0 | H88: =IF(H80=YEAR('Summary Inputs & Assumptions'!$T$7),-H52,IF(H80=0,0,-(H52-G52))) -> 0 | I88: =IF(I80=YEAR('Summary Inputs & Assumptions'!$T$7),-I52,IF(I80=0,0,-(I52-H52))) -> 0 | J88: =IF(J80=YEAR('Summary Inputs & Assumptions'!$T$7),-J52,IF(J80=0,0,-(J52-I52))) -> 0 | K88: =IF(K80=YEAR('Summary Inputs & Assumptions'!$T$7),-K52,IF(K80=0,0,-(K52-J52))) -> 0 | ... AG88: =IF(AG80=YEAR('Summary Inputs & Assumptions'!$T$7),-AG52,IF(AG80=0,0,-(AG52-AF52))) -> 0
C90: Cashflow from Financing
C91: Debt Servicing | D91: =D61 -> 1605564 | E91: =IF(E80=0,0,(E61-D61)) -> -10961.252 | F91: =IF(F80=0,0,(F61-E61)) -> -85987.26 | G91: =IF(G80=0,0,(G61-F61)) -> -89489.191 | H91: =IF(H80=0,0,(H61-G61)) -> -93163.293 | I91: =IF(I80=0,0,(I61-H61)) -> -97018.077 | J91: =IF(J80=0,0,(J61-I61)) -> -101062.48 | K91: =IF(K80=0,0,(K61-J61)) -> -105305.88 | L91: =IF(L80=0,0,(L61-K61)) -> -109758.12 | ... AG91: =IF(AG80=0,0,(AG61-AF61)) -> 0
C92: Equity | D92: =IF(D80=YEAR('Summary Inputs & Assumptions'!$T$7),(D68+D67),IF(D80=0,0,(D68+D67)-(C67+C68))) -> 2770002.1 | E92: =IF(E80=YEAR('Summary Inputs & Assumptions'!$T$7),(E68+E67),IF(E80=0,0,(E68+E67)-(D67+D68))) -> 1363633.9 | F92: =IF(F80=YEAR('Summary Inputs & Assumptions'!$T$7),(F68+F67),IF(F80=0,0,(F68+F67)-(E67+E68))) -> 0 | G92: =IF(G80=YEAR('Summary Inputs & Assumptions'!$T$7),(G68+G67),IF(G80=0,0,(G68+G67)-(F67+F68))) -> 0 | H92: =IF(H80=YEAR('Summary Inputs & Assumptions'!$T$7),(H68+H67),IF(H80=0,0,(H68+H67)-(G67+G68))) -> 0 | I92: =IF(I80=YEAR('Summary Inputs & Assumptions'!$T$7),(I68+I67),IF(I80=0,0,(I68+I67)-(H67+H68))) -> 0 | J92: =IF(J80=YEAR('Summary Inputs & Assumptions'!$T$7),(J68+J67),IF(J80=0,0,(J68+J67)-(I67+I68))) -> 0 | K92: =IF(K80=YEAR('Summary Inputs & Assumptions'!$T$7),(K68+K67),IF(K80=0,0,(K68+K67)-(J67+J68))) -> 0 | ... AG92: =IF(AG80=YEAR('Summary Inputs & Assumptions'!$T$7),(AG68+AG67),IF(AG80=0,0,(AG68+AG67)-(AF67+AF68))) -> 0
C93: Total Cashflow from Financing | D93: =SUM(D91:D92) -> 4375566.1 | E93: =SUM(E91:E92) -> 1352672.7 | F93: =SUM(F91:F92) -> -85987.26 | G93: =SUM(G91:G92) -> -89489.191 | H93: =SUM(H91:H92) -> -93163.293 | I93: =SUM(I91:I92) -> -97018.077 | J93: =SUM(J91:J92) -> -101062.48 | K93: =SUM(K91:K92) -> -105305.88 | ... AG93: =SUM(AG91:AG92) -> 0
C96: Net Change in Cash | D96: =D93+D88+D85 -> 4592703.5 | E96: =E93+E88+E85 -> -3283429.1 | F96: =F93+F88+F85 -> 236823.46 | G96: =G93+G88+G85 -> 227646.54 | H96: =H93+H88+H85 -> 218109.2 | I96: =I93+I88+I85 -> 208193.76 | J96: =J93+J88+J85 -> 197881.64 | K96: =K93+K88+K85 -> 187153.37 | ... AG96: =AG93+AG88+AG85 -> 0
C97: Beginning Cash Balance | E97: =IF(E80=0,0,D98) -> 4592703.5 | F97: =IF(F80=0,0,E98) -> 1309274.4 | G97: =IF(G80=0,0,F98) -> 1546097.8 | H97: =IF(H80=0,0,G98) -> 1773744.4 | I97: =IF(I80=0,0,H98) -> 1991853.6 | J97: =IF(J80=0,0,I98) -> 2200047.3 | K97: =IF(K80=0,0,J98) -> 2397929 | L97: =IF(L80=0,0,K98) -> 2585082.3 | ... AG97: =IF(AG80=0,0,AF98) -> 0
C98: Ending Cash Balance | D98: =SUM(D96:D97) -> 4592703.5 | E98: =SUM(E96:E97) -> 1309274.4 | F98: =SUM(F96:F97) -> 1546097.8 | G98: =SUM(G96:G97) -> 1773744.4 | H98: =SUM(H96:H97) -> 1991853.6 | I98: =SUM(I96:I97) -> 2200047.3 | J98: =SUM(J96:J97) -> 2397929 | K98: =SUM(K96:K97) -> 2585082.3 | ... AG98: =SUM(AG96:AG97) -> 0

Sheet Debt
B2: Max Debt | C2: =NPV($C$4,Debt!G8:G42) -> 1605564 | E2: P50 DSCR | F2: P99 DSCR
B3: Amortization period | C3: =Amortization_period -> 15 | E3: ='Summary Inputs & Assumptions'!Q39 -> 1.5 | F3: ='Summary Inputs & Assumptions'!Q40 -> 1
B4: Swapped Interest Rate | C4: =Interest_Rate -> 0.05
E6: Debt Service | H6: Principal
B7: Year | C7: ='Financial Statements'!C35 -> EBITDA P50 | D7: ='Financial Statements'!C37 -> EBITDA P99 | E7: P50 | F7: P99 | G7: Debt Service | H7: Bgn Balance | I7: End Balance | J7: Total Interest Expense | K7: Principal Payment
A8: 1 | B8: =YEAR('Summary Inputs & Assumptions'!T7) -> 2022 | C8: {=IF(B8="",0,TRANSPOSE('Financial Statements'!$D$35:$AG$35))} -> 136859.18 | D8: {=TRANSPOSE('Financial Statements'!$D$37:$AG$37)} -> 115075.33 | E8: =IF(B8="",0,C8/$E$3) -> 91239.452 | F8: =IF(B8="",0,D8/$F$3) -> 115075.33 | G8: =IF(A8<=$C$3,MIN(E8,F8),0) -> 91239.452 | H8: =C2 -> 1605564 | I8: =H8-K8 -> 1594602.7 | J8: =H8*$C$4 -> 80278.2 | K8: =G8-J8 -> 10961.252
A9: 2 | B9: =IF(A9<='Summary Inputs & Assumptions'!$Q$41,Debt!B8+1,"") -> 2023 | C9: 248576.1 | D9: 208939.84 | E9: =IF(B9="",0,C9/$E$3) -> 165717.4 | F9: =IF(B9="",0,D9/$F$3) -> 208939.84 | G9: =IF(A9<=$C$3,MIN(E9,F9),0) -> 165717.4 | H9: =I8 -> 1594602.7 | I9: =H9-MIN(K9,I8) -> 1508615.5 | J9: =H9*$C$4 -> 79730.137 | K9: =G9-J9 -> 85987.26
A10: 3 | B10: =IF(A10<='Summary Inputs & Assumptions'!$Q$41,Debt!B9+1,"") -> 2024 | C10: 247379.95 | D10: 207862.6 | E10: =IF(B10="",0,C10/$E$3) -> 164919.97 | F10: =IF(B10="",0,D10/$F$3) -> 207862.6 | G10: =IF(A10<=$C$3,MIN(E10,F10),0) -> 164919.97 | H10: =I9 -> 1508615.5 | I10: =H10-MIN(K10,I9) -> 1419126.3 | J10: =H10*$C$4 -> 75430.774 | K10: =G10-J10 -> 89489.191
A11: 4 | B11: =IF(A11<='Summary Inputs & Assumptions'!$Q$41,Debt!B10+1,"") -> 2025 | C11: 246179.41 | D11: 206780.62 | E11: =IF(B11="",0,C11/$E$3) -> 164119.61 | F11: =IF(B11="",0,D11/$F$3) -> 206780.62 | G11: =IF(A11<=$C$3,MIN(E11,F11),0) -> 164119.61 | H11: =I10 -> 1419126.3 | I11: =H11-MIN(K11,I10) -> 1325963 | J11: =H11*$C$4 -> 70956.315 | K11: =G11-J11 -> 93163.293
A12: 5 | B12: =IF(A12<='Summary Inputs & Assumptions'!$Q$41,Debt!B11+1,"") -> 2026 | C12: 244974.34 | D12: 205693.74 | E12: =IF(B12="",0,C12/$E$3) -> 163316.23 | F12: =IF(B12="",0,D12/$F$3) -> 205693.74 | G12: =IF(A12<=$C$3,MIN(E12,F12),0) -> 163316.23 | H12: =I11 -> 1325963 | I12: =H12-MIN(K12,I11) -> 1228944.9 | J12: =H12*$C$4 -> 66298.15 | K12: =G12-J12 -> 97018.077
A13: 6 | B13: =IF(A13<='Summary Inputs & Assumptions'!$Q$41,Debt!B12+1,"") -> 2027 | C13: 243764.59 | D13: 204601.83 | E13: =IF(B13="",0,C13/$E$3) -> 162509.72 | F13: =IF(B13="",0,D13/$F$3) -> 204601.83 | G13: =IF(A13<=$C$3,MIN(E13,F13),0) -> 162509.72 | H13: =I12 -> 1228944.9 | I13: =H13-MIN(K13,I12) -> 1127882.4 | J13: =H13*$C$4 -> 61447.246 | K13: =G13-J13 -> 101062.48
A14: 7 | B14: =IF(A14<='Summary Inputs & Assumptions'!$Q$41,Debt!B13+1,"") -> 2028 | C14: 242550 | D14: 203504.73 | E14: =IF(B14="",0,C14/$E$3) -> 161700 | F14: =IF(B14="",0,D14/$F$3) -> 203504.73 | G14: =IF(A14<=$C$3,MIN(E14,F14),0) -> 161700 | H14: =I13 -> 1127882.4 | I14: =H14-MIN(K14,I13) -> 1022576.6 | J14: =H14*$C$4 -> 56394.122 | K14: =G14-J14 -> 105305.88
A15: 8 | B15: =IF(A15<='Summary Inputs & Assumptions'!$Q$41,Debt!B14+1,"") -> 2029 | C15: 241330.42 | D15: 202402.29 | E15: =IF(B15="",0,C15/$E$3) -> 160886.95 | F15: =IF(B15="",0,D15/$F$3) -> 202402.29 | G15: =IF(A15<=$C$3,MIN(E15,F15),0) -> 160886.95 | H15: =I14 -> 1022576.6 | I15: =H15-MIN(K15,I14) -> 912818.46 | J15: =H15*$C$4 -> 51128.829 | K15: =G15-J15 -> 109758.12
A16: 9 | B16: =IF(A16<='Summary Inputs & Assumptions'!$Q$41,Debt!B15+1,"") -> 2030 | C16: 240105.69 | D16: 201294.34 | E16: =IF(B16="",0,C16/$E$3) -> 160070.46 | F16: =IF(B16="",0,D16/$F$3) -> 201294.34 | G16: =IF(A16<=$C$3,MIN(E16,F16),0) -> 160070.46 | H16: =I15 -> 912818.46 | I16: =H16-MIN(K16,I15) -> 798388.92 | J16: =H16*$C$4 -> 45640.923 | K16: =G16-J16 -> 114429.54
A17: 10 | B17: =IF(A17<='Summary Inputs & Assumptions'!$Q$41,Debt!B16+1,"") -> 2031 | C17: 238875.65 | D17: 200180.74 | E17: =IF(B17="",0,C17/$E$3) -> 159250.44 | F17: =IF(B17="",0,D17/$F$3) -> 200180.74 | G17: =IF(A17<=$C$3,MIN(E17,F17),0) -> 159250.44 | H17: =I16 -> 798388.92 | I17: =H17-MIN(K17,I16) -> 679057.93 | J17: =H17*$C$4 -> 39919.446 | K17: =G17-J17 -> 119330.99
A18: 11 | B18: =IF(A18<='Summary Inputs & Assumptions'!$Q$41,Debt!B17+1,"") -> 2032 | C18: 237640.15 | D18: 199061.32 | E18: =IF(B18="",0,C18/$E$3) -> 158426.76 | F18: =IF(B18="",0,D18/$F$3) -> 199061.32 | G18: =IF(A18<=$C$3,MIN(E18,F18),0) -> 158426.76 | H18: =I17 -> 679057.93 | I18: =H18-MIN(K18,I17) -> 554584.06 | J18: =H18*$C$4 -> 33952.896 | K18: =G18-J18 -> 124473.87
A19: 12 | B19: =IF(A19<='Summary Inputs & Assumptions'!$Q$41,Debt!B18+1,"") -> 2033 | C19: 236399 | D19: 197935.91 | E19: =IF(B19="",0,C19/$E$3) -> 157599.33 | F19: =IF(B19="",0,D19/$F$3) -> 197935.91 | G19: =IF(A19<=$C$3,MIN(E19,F19),0) -> 157599.33 | H19: =I18 -> 554584.06 | I19: =H19-MIN(K19,I18) -> 424713.93 | J19: =H19*$C$4 -> 27729.203 | K19: =G19-J19 -> 129870.13
A20: 13 | B20: =IF(A20<='Summary Inputs & Assumptions'!$Q$41,Debt!B19+1,"") -> 2034 | C20: 235152.04 | D20: 196804.34 | E20: =IF(B20="",0,C20/$E$3) -> 156768.03 | F20: =IF(B20="",0,D20/$F$3) -> 196804.34 | G20: =IF(A20<=$C$3,MIN(E20,F20),0) -> 156768.03 | H20: =I19 -> 424713.93 | I20: =H20-MIN(K20,I19) -> 289181.6 | J20: =H20*$C$4 -> 21235.696 | K20: =G20-J20 -> 135532.33
... A37: 30 | B37: =IF(A37<='Summary Inputs & Assumptions'!$Q$41,Debt!B36+1,"") | C37: 0 | D37: 0 | E37: =IF(B37="",0,C37/$E$3) -> 0 | F37: =IF(B37="",0,D37/$F$3) -> 0 | G37: =IF(A37<=$C$3,MIN(E37,F37),0) -> 0 | H37: =I36 -> 0 | I37: =H37-MIN(K37,I36) -> 0 | J37: =H37*$C$4 -> 0 | K37: =G37-J37 -> 0
A38: 31 | B38: =IF(A38<='Summary Inputs & Assumptions'!$Q$41,Debt!B37+1,"") | E38: =IF(B38="",0,C38/$E$3) -> 0 | F38: =IF(B38="",0,D38/$F$3) -> 0 | G38: =IF(A38<=$C$3,MIN(E38,F38),0) -> 0 | H38: =I37 -> 0 | I38: =H38-MIN(K38,I37) -> 0 | J38: =H38*$C$4 -> 0 | K38: =G38-J38 -> 0
A39: 32 | B39: =IF(A39<='Summary Inputs & Assumptions'!$Q$41,Debt!B38+1,"") | E39: =IF(B39="",0,C39/$E$3) -> 0 | F39: =IF(B39="",0,D39/$F$3) -> 0 | G39: =IF(A39<=$C$3,MIN(E39,F39),0) -> 0 | H39: =I38 -> 0 | I39: =H39-MIN(K39,I38) -> 0 | J39: =H39*$C$4 -> 0 | K39: =G39-J39 -> 0
A40: 33 | B40: =IF(A40<='Summary Inputs & Assumptions'!$Q$41,Debt!B39+1,"") | E40: =IF(B40="",0,C40/$E$3) -> 0 | F40: =IF(B40="",0,D40/$F$3) -> 0 | G40: =IF(A40<=$C$3,MIN(E40,F40),0) -> 0 | H40: =I39 -> 0 | I40: =H40-MIN(K40,I39) -> 0 | J40: =H40*$C$4 -> 0 | K40: =G40-J40 -> 0
A41: 34 | B41: =IF(A41<='Summary Inputs & Assumptions'!$Q$41,Debt!B40+1,"") | E41: =IF(B41="",0,C41/$E$3) -> 0 | F41: =IF(B41="",0,D41/$F$3) -> 0 | G41: =IF(A41<=$C$3,MIN(E41,F41),0) -> 0 | H41: =I40 -> 0 | I41: =H41-MIN(K41,I40) -> 0 | J41: =H41*$C$4 -> 0 | K41: =G41-J41 -> 0
A42: 35 | B42: =IF(A42<='Summary Inputs & Assumptions'!$Q$41,Debt!B41+1,"") | E42: =IF(B42="",0,C42/$E$3) -> 0 | F42: =IF(B42="",0,D42/$F$3) -> 0 | G42: =IF(A42<=$C$3,MIN(E42,F42),0) -> 0 | H42: =I41 -> 0 | I42: =H42-MIN(K42,I41) -> 0 | J42: =H42*$C$4 -> 0 | K42: =G42-J42 -> 0
G43: =IF(A43<=$C$3,MIN(E43,F43),0) -> 0 | J43: =H43*$C$4 -> 0 | K43: =G43-J43 -> 0
G44: =IF(A44<=$C$3,MIN(E44,F44),0) -> 0
B45: Total | C45: =SUM(C8:C44) -> 3506325.6 | D45: =SUM(D8:D44) -> 2940326.1 | E45: =SUM(E8:E28) -> 2337550.4 | F45: =SUM(F8:F28) -> 2940326.1 | H45: =SUM(H8:H28) -> 14639728 | I45: =SUM(I8:I28) -> 13034164

Sheet Capital Contribution Schedule
B3: Total Capital Required | C3: ='Summary Inputs & Assumptions'!L16 -> 5739200 | D3: =C3/$C$3 -> 1
B4: Total Debt | C4: ='Financial Statements'!D61 -> 1605564 | D4: =C4/$C$3 -> 0.27975397
B5: Total Equity | C5: =C3-C4 -> 4133636 | D5: =C5/$C$3 -> 0.72024603
B7: Total Tax Equity | C7: ='Summary Inputs & Assumptions'!L39*'Summary Inputs & Assumptions'!L38 -> 1704542.4 | D7: =C7/$C$5 -> 0.41235909
B8: GP Equity | C8: =C5-C7 -> 2429093.6 | D8: =C8/$C$5 -> 0.58764091
B13: Contribution Schedule | C13: Paid In Capital (Tax Equity) | D13: Paid in Capital GP | E13: Total
B15: =YEAR('Summary Inputs & Assumptions'!T7) -> 2022 | C15: =SUMIFS('Summary Inputs & Assumptions'!$U$15:$U$18,'Summary Inputs & Assumptions'!$Q$7:$Q$10,'Capital Contribution Schedule'!B15)*$C$7 -> 340908.48 | D15: =SUMIFS('Summary Inputs & Assumptions'!$V$15:$V$18,'Summary Inputs & Assumptions'!$Q$7:$Q$10,'Capital Contribution Schedule'!B15)*$C$8 -> 2429093.6 | E15: =C15+D15 -> 2770002.1
B16: =B15+1 -> 2023 | C16: =SUMIFS('Summary Inputs & Assumptions'!$U$15:$U$18,'Summary Inputs & Assumptions'!$Q$7:$Q$10,'Capital Contribution Schedule'!B16)*$C$7 -> 1363633.9 | D16: =SUMIFS('Summary Inputs & Assumptions'!$V$15:$V$18,'Summary Inputs & Assumptions'!$Q$7:$Q$10,'Capital Contribution Schedule'!B16)*$C$8 -> 0 | E16: =C16+D16 -> 1363633.9
B17: =B16+1 -> 2024 | C17: =SUMIFS('Summary Inputs & Assumptions'!$U$15:$U$18,'Summary Inputs & Assumptions'!$Q$7:$Q$10,'Capital Contribution Schedule'!B17)*$C$7 -> 0 | D17: =SUMIFS('Summary Inputs & Assumptions'!$V$15:$V$18,'Summary Inputs & Assumptions'!$Q$7:$Q$10,'Capital Contribution Schedule'!B17)*$C$8 -> 0 | E17: =C17+D17 -> 0
B18: =B17+1 -> 2025 | C18: =SUMIFS('Summary Inputs & Assumptions'!$U$15:$U$18,'Summary Inputs & Assumptions'!$Q$7:$Q$10,'Capital Contribution Schedule'!B18)*$C$7 -> 0 | D18: =SUMIFS('Summary Inputs & Assumptions'!$V$15:$V$18,'Summary Inputs & Assumptions'!$Q$7:$Q$10,'Capital Contribution Schedule'!B18)*$C$8 -> 0 | E18: =C18+D18 -> 0
B19: =B18+1 -> 2026 | C19: =SUMIFS('Summary Inputs & Assumptions'!$U$15:$U$18,'Summary Inputs & Assumptions'!$Q$7:$Q$10,'Capital Contribution Schedule'!B19)*$C$7 -> 0 | D19: =SUMIFS('Summary Inputs & Assumptions'!$V$15:$V$18,'Summary Inputs & Assumptions'!$Q$7:$Q$10,'Capital Contribution Schedule'!B19)*$C$8 -> 0 | E19: =C19+D19 -> 0
B20: =B19+1 -> 2027 | C20: =SUMIFS('Summary Inputs & Assumptions'!$U$15:$U$18,'Summary Inputs & Assumptions'!$Q$7:$Q$10,'Capital Contribution Schedule'!B20)*$C$7 -> 0 | D20: =SUMIFS('Summary Inputs & Assumptions'!$V$15:$V$18,'Summary Inputs & Assumptions'!$Q$7:$Q$10,'Capital Contribution Schedule'!B20)*$C$8 -> 0 | E20: =C20+D20 -> 0
B21: =B20+1 -> 2028 | C21: =SUMIFS('Summary Inputs & Assumptions'!$U$15:$U$18,'Summary Inputs & Assumptions'!$Q$7:$Q$10,'Capital Contribution Schedule'!B21)*$C$7 -> 0 | D21: =SUMIFS('Summary Inputs & Assumptions'!$V$15:$V$18,'Summary Inputs & Assumptions'!$Q$7:$Q$10,'Capital Contribution Schedule'!B21)*$C$8 -> 0 | E21: =C21+D21 -> 0
B22: =B21+1 -> 2029 | C22: =SUMIFS('Summary Inputs & Assumptions'!$U$15:$U$18,'Summary Inputs & Assumptions'!$Q$7:$Q$10,'Capital Contribution Schedule'!B22)*$C$7 -> 0 | D22: =SUMIFS('Summary Inputs & Assumptions'!$V$15:$V$18,'Summary Inputs & Assumptions'!$Q$7:$Q$10,'Capital Contribution Schedule'!B22)*$C$8 -> 0 | E22: =C22+D22 -> 0
B23: =B22+1 -> 2030 | C23: =SUMIFS('Summary Inputs & Assumptions'!$U$15:$U$18,'Summary Inputs & Assumptions'!$Q$7:$Q$10,'Capital Contribution Schedule'!B23)*$C$7 -> 0 | D23: =SUMIFS('Summary Inputs & Assumptions'!$V$15:$V$18,'Summary Inputs & Assumptions'!$Q$7:$Q$10,'Capital Contribution Schedule'!B23)*$C$8 -> 0 | E23: =C23+D23 -> 0
B24: =B23+1 -> 2031 | C24: =SUMIFS('Summary Inputs & Assumptions'!$U$15:$U$18,'Summary Inputs & Assumptions'!$Q$7:$Q$10,'Capital Contribution Schedule'!B24)*$C$7 -> 0 | D24: =SUMIFS('Summary Inputs & Assumptions'!$V$15:$V$18,'Summary Inputs & Assumptions'!$Q$7:$Q$10,'Capital Contribution Schedule'!B24)*$C$8 -> 0 | E24: =C24+D24 -> 0
B25: =B24+1 -> 2032 | C25: =SUMIFS('Summary Inputs & Assumptions'!$U$15:$U$18,'Summary Inputs & Assumptions'!$Q$7:$Q$10,'Capital Contribution Schedule'!B25)*$C$7 -> 0 | D25: =SUMIFS('Summary Inputs & Assumptions'!$V$15:$V$18,'Summary Inputs & Assumptions'!$Q$7:$Q$10,'Capital Contribution Schedule'!B25)*$C$8 -> 0 | E25: =C25+D25 -> 0
B26: =B25+1 -> 2033 | C26: =SUMIFS('Summary Inputs & Assumptions'!$U$15:$U$18,'Summary Inputs & Assumptions'!$Q$7:$Q$10,'Capital Contribution Schedule'!B26)*$C$7 -> 0 | D26: =SUMIFS('Summary Inputs & Assumptions'!$V$15:$V$18,'Summary Inputs & Assumptions'!$Q$7:$Q$10,'Capital Contribution Schedule'!B26)*$C$8 -> 0 | E26: =C26+D26 -> 0
B27: =B26+1 -> 2034 | C27: =SUMIFS('Summary Inputs & Assumptions'!$U$15:$U$18,'Summary Inputs & Assumptions'!$Q$7:$Q$10,'Capital Contribution Schedule'!B27)*$C$7 -> 0 | D27: =SUMIFS('Summary Inputs & Assumptions'!$V$15:$V$18,'Summary Inputs & Assumptions'!$Q$7:$Q$10,'Capital Contribution Schedule'!B27)*$C$8 -> 0 | E27: =C27+D27 -> 0
... B34: =B33+1 -> 2041 | C34: =SUMIFS('Summary Inputs & Assumptions'!$U$15:$U$18,'Summary Inputs & Assumptions'!$Q$7:$Q$10,'Capital Contribution Schedule'!B34)*$C$7 -> 0 | D34: =SUMIFS('Summary Inputs & Assumptions'!$V$15:$V$18,'Summary Inputs & Assumptions'!$Q$7:$Q$10,'Capital Contribution Schedule'!B34)*$C$8 -> 0 | E34: =C34+D34 -> 0
C36: =SUM(C15:C22) -> 1704542.4 | D36: =SUM(D14:D22) -> 2429093.6
